{
  "id": "pl-du-2021-2338",
  "type": "statute",
  "title": "Ustawa z dnia 17 listopada 2021 r. o zmianie ustawy o ochronie zwierząt wykorzystywanych do celów naukowych lub edukacyjnych",
  "title_en": "",
  "short_name": "pl-du-2021-2338",
  "status": "amended",
  "issued_date": "2021-11-17",
  "in_force_date": "2021-12-17",
  "url": "https://api.sejm.gov.pl/eli/acts/DU/2021/2338",
  "provisions": [
    {
      "provision_ref": "art1",
      "section": "1",
      "title": "Art. 1",
      "content": "W ustawie z dnia 15 stycznia 2015 r. o ochronie zwierząt wykorzystywanych do celów naukowych lub edukacyjnych ( Dz. U. z 2021 r. poz. 1331 ) wprowadza się następujące zmiany: 1) w art. 2: a) w ust. 1: - w pkt 2: - - w lit. a wyrazy „świnka morska” zastępuje się wyrazami „kawia domowa” , - - w lit. b po wyrazach „w niewoli” dodaje się wyrazy „albo pozyskiwane z kolonii samowystarczalnych” , - - uchyla się lit. c, - pkt 9 otrzymuje brzmienie: „ 9) hodowca - osobę fizyczną, osobę prawną lub jednostkę organizacyjną nieposiadającą osobowości prawnej, która hoduje zwierzęta laboratoryjne w celu wykorzystania ich w procedurach lub aby wykorzystać ich narządy lub tkanki do celów określonych w art. 3 lub która hoduje inne zwierzęta głównie w tych celach; ” , - w pkt 11: - - po wyrazach „w procedurach” dodaje się wyrazy „lub uśmierca zwierzęta, aby wykorzystać ich narządy lub tkanki do celów określonych w art. 3” , - - kropkę zastępuje się średnikiem i dodaje się pkt 12 w brzmieniu: „ 12) kolonia samowystarczalna - kolonię, w której zwierzęta z rzędu naczelnych są hodowane wyłącznie w ramach kolonii lub są pozyskiwane z innych kolonii, ale nie są zwierzętami dzikimi, oraz w której zwierzęta są utrzymywane w sposób zapewniający ich przyzwyczajenie do ludzi. ” , b) uchyla się ust. 3; 2) po art. 3 dodaje się art. 3a i art. 3b w brzmieniu: „ Art. 3a. Hodowca, dostawca i użytkownik zapewniają: 1) stosowanie - zawsze, gdy jest to możliwe, zamiast danej procedury - metody lub strategii badawczej, która jest zadowalająca pod względem naukowym i nie obejmuje wykorzystywania zwierząt (zasada zastąpienia); 2) zredukowanie do minimum liczby zwierząt wykorzystywanych w procedurach, bez uszczerbku dla celów tych procedur (zasada ograniczenia); 3) udoskonalenie hodowli zwierząt, ich utrzymywania, opieki nad nimi i metod stosowanych w procedurach tak, aby u zwierząt zostały wyeliminowane lub ograniczone do minimum potencjalne: ból, cierpienie, dystres lub trwałe uszkodzenie ich organizmu (zasada udoskonalenia). Art. 3b. 1. W przypadku konieczności uśmiercenia zwierzęcia przez hodowcę, dostawcę lub użytkownika zwierzę uśmierca osoba spełniająca wymagania określone w art. 20 ust. 2, wyłącznie z zastosowaniem metod określonych w załączniku nr IV do dyrektywy Parlamentu Europejskiego i Rady 2010/63/UE z dnia 22 września 2010 r. w sprawie ochrony zwierząt wykorzystywanych do celów naukowych ( Dz. Urz. UE L 276 z 20.10.2010, str. 33 , z późn. zm.) 2) Zmiany wymienionej dyrektywy zostały ogłoszone w Dz. Urz. UE L 170 z 25.06.2019, str. 115. . 2. Zwierzę uśmierca się w ośrodku. Zwierzę może zostać uśmiercone poza ośrodkiem jedynie wtedy, gdy procedura jest wykonywana poza ośrodkiem. 3. Zwierzę uśmierca się w sposób ograniczający do minimum jego ból, cierpienie i dystres. 4. Przepisów ust. 1 i 2 nie stosuje się w przypadku nagłej konieczności uśmiercenia zwierzęcia ze względu na jego dobrostan lub zagrożenie dla zdrowia ludzi, zwierząt lub środowiska naturalnego. 5. Krajowa Komisja Etyczna do Spraw Doświadczeń na Zwierzętach może ustanawiać odstępstwa od wymagania uśmiercania zwierząt wyłącznie z zastosowaniem metod określonych w załączniku nr IV do dyrektywy Parlamentu Europejskiego i Rady 2010/63/UE z dnia 22 września 2010 r. w sprawie ochrony zwierząt wykorzystywanych do celów naukowych i dopuścić stosowanie innej metody, jeżeli na podstawie dowodów naukowych uzna, że ta metoda jest co najmniej równie humanitarna. ” ; 3) w art. 5: a) ust. 1 otrzymuje brzmienie: „ 1. Procedury są wykonywane zgodnie z zasadami zastąpienia, ograniczenia i udoskonalenia. ” , b) po ust. 2 dodaje się ust. 2a w brzmieniu: „ 2a. Niedopuszczalne jest wykonanie procedury, jeżeli na mocy prawodawstwa Unii Europejskiej, w szczególności w zakresie pasz, produktów biobójczych, produktów leczniczych, substancji chemicznych, środków ochrony roślin, wyrobów medycznych lub żywności, jest uznawana inna metoda lub strategia testowania, która pozwala na uzyskanie odpowiednich wyników bez wykorzystywania zwierząt. ” ; 4) w art. 6: a) ust. 1 otrzymuje brzmienie: „ 1. Procedury planuje się i wykonuje tak, aby w największym możliwym zakresie unikać w ich wyniku śmierci zwierząt i zastępować ją wczesnym i humanitarnym zakończeniem tych procedur polegającym na jak najwcześniejszym uśmiercaniu zwierząt w przypadkach występowania objawów bólu, cierpienia lub dystresu, których nie można złagodzić, a których trwanie nie jest uzasadnione z naukowego i etycznego punktu widzenia. ” , b) uchyla się ust. 3; 5) w art. 7 wprowadzenie do wyliczenia otrzymuje brzmienie: „ Lokalna komisja etyczna do spraw doświadczeń na zwierzętach może, na podstawie uzasadnienia naukowego przedstawionego przez użytkownika, udzielić zgody na wykorzystanie w procedurze zwierząt: ” ; 6) w art. 8: a) ust. 2 otrzymuje brzmienie: „ 2. Lokalna komisja etyczna do spraw doświadczeń na zwierzętach, na podstawie uzasadnienia naukowego przedstawionego przez użytkownika, może: 1) udzielić zgody na wykorzystanie w procedurze zwierząt, o których mowa w ust. 1 pkt 2, jeżeli celów określonych w art. 3 nie można osiągnąć z wykorzystaniem zwierząt laboratoryjnych; 2) udzielić, w wyjątkowych przypadkach, zgody na wykorzystanie w procedurze zwierząt, o których mowa w ust. 1 pkt 3, jeżeli celem procedury jest zbadanie zdrowia i dobrostanu tych zwierząt lub zapobieżenie poważnemu zagrożeniu powodowanemu przez te zwierzęta dla zdrowia ludzi lub zwierząt lub dla środowiska i cel ten można osiągnąć wyłącznie z wykorzystaniem tych zwierząt. ” , b) dodaje się ust. 3 i 4 w brzmieniu: „ 3. Pozyskiwania zwierząt, o których mowa w ust. 1 pkt 2, dokonują osoby posiadające doświadczenie w zakresie pozyskiwania zwierząt dzikich z gatunków zaplanowanych do wykorzystania w procedurze za pomocą metod niepowodujących u zwierząt możliwych do uniknięcia: bólu, cierpienia, dystresu lub trwałego uszkodzenia ich organizmu. 4. Zwierzęta, o których mowa w ust. 1 pkt 2, u których w trakcie pozyskiwania lub po jego zakończeniu stwierdzono zranienie lub zły stan zdrowia, są poddawane badaniu przez lekarza weterynarii lub przez inną osobę posiadającą kwalifikacje w zakresie znajomości anatomii, fizjologii i zachowań właściwych dla gatunków tych zwierząt, a następnie czynnościom minimalizującym u zwierząt ból, cierpienie, dystres lub trwałe uszkodzenie ich organizmu. Lokalna komisja etyczna do spraw doświadczeń na zwierzętach może, na podstawie uzasadnienia naukowego przedstawionego przez użytkownika, udzielić zgody na niepodejmowanie tych czynności. ” ; 7) w art. 9: a) ust. 2 otrzymuje brzmienie: „ 2. Lokalna komisja etyczna do spraw doświadczeń na zwierzętach może, na podstawie uzasadnienia naukowego przedstawionego przez użytkownika, udzielić zgody na wykonanie procedury w: 1) miejscu innym niż określone w ust. 1 pkt 2, jeżeli celu procedury nie da się osiągnąć, gdy wykonuje się ją w ośrodku użytkownika; 2) środowisku życia zwierzęcia dzikiego, jeżeli cel procedury może zostać osiągnięty przez jej wykonanie w tym środowisku i zmniejsza to stres zwierzęcia związany z jej wykonaniem. ” , b) uchyla się ust. 3; 8) w art. 10 ust. 2 otrzymuje brzmienie: „ 2. Procedury kwalifikuje się do kategorii wymienionych w ust. 1 zgodnie z załącznikiem nr VIII do dyrektywy Parlamentu Europejskiego i Rady 2010/63/UE z dnia 22 września 2010 r. w sprawie ochrony zwierząt wykorzystywanych do celów naukowych . ” ; 9) w art. 13 w ust. 3: a) wprowadzenie do wyliczenia otrzymuje brzmienie: „ W przypadku, o którym mowa w ust. 2, procedura może być wykonywana bez zastosowania znieczuleń, produktów lub metod, o których mowa w tym przepisie, jedynie wtedy, gdy ich zastosowanie: ” , b) część wspólna otrzymuje brzmienie: „ - po uzyskaniu zgody lokalnej komisji etycznej do spraw doświadczeń na zwierzętach, na podstawie przedstawionego przez użytkownika uzasadnienia naukowego dla odstąpienia od zastosowania takiego znieczulenia, takiego produktu lub takiej metody. ” ; 10) w art. 15 w ust. 2 wprowadzenie do wyliczenia otrzymuje brzmienie: „ Hodowca, dostawca lub użytkownik może przywrócić zwierzę wykorzystane lub przeznaczone do wykorzystania w procedurze do właściwego dla gatunku tego zwierzęcia siedliska przyrodniczego albo miejsca chowu lub hodowli albo znaleźć dla niego nowego opiekuna jedynie wtedy, gdy: ” ; 11) uchyla się art. 16; 12) po art. 16 dodaje się art. 16a w brzmieniu: „ Art. 16a. Lokalna komisja etyczna do spraw doświadczeń na zwierzętach może, na podstawie uzasadnienia naukowego przedstawionego przez użytkownika, udzielić zgody na zastosowanie innej metody uśmiercenia zwierzęcia wykorzystywanego w procedurze niż metody: 1) określone w załączniku nr IV do dyrektywy Parlamentu Europejskiego i Rady 2010/63/UE z dnia 22 września 2010 r. w sprawie ochrony zwierząt wykorzystywanych do celów naukowych , 2) dopuszczone do stosowania zgodnie z art. 3b ust. 5 - jeżeli cel procedury nie może zostać osiągnięty przez zastosowanie metod, o których mowa w pkt 1 i 2. ” ; 13) w art. 17 w ust. 1 we wprowadzeniu do wyliczenia wyrazy „Podmiot prowadzący działalność w zakresie wykorzystywania zwierząt od celów naukowych lub edukacyjnych” zastępuje się wyrazami „Hodowca, dostawca i użytkownik” ; 14) w art. 18: a) we wprowadzeniu do wyliczenia wyrazy „Podmiot prowadzący działalność w zakresie wykorzystywania zwierząt od celów naukowych lub edukacyjnych jako użytkownik” zastępuje się wyrazem „Użytkownik” , b) w pkt 2 lit. a otrzymuje brzmienie: „ a) zapewnić uzyskiwanie wiarygodnych wyników procedur z wykorzystaniem jak najmniejszej liczby zwierząt, ” ; 15) art. 19 otrzymuje brzmienie: „ Art. 19. Minister właściwy do spraw rolnictwa określi, w drodze rozporządzenia, minimalne wymagania: 1) jakie musi spełniać ośrodek, 2) w zakresie opieki nad zwierzętami utrzymywanymi w ośrodku, w tym pozyskanymi zwierzętami dzikimi, 3) w zakresie transportu zwierząt dzikich - biorąc pod uwagę potrzeby fizjologiczne i etologiczne gatunków zwierząt pozyskiwanych lub utrzymywanych w ośrodku oraz konieczność zapewnienia utrzymywanym w nim zwierzętom dobrostanu i prawidłowego stanu zdrowia, a także właściwych warunków opieki. ” ; 16) w art. 20: a) dotychczasową treść oznacza się jako ust. 1 i we wprowadzeniu do wyliczenia wyrazy „Podmiot, o którym mowa w art. 17 ust. 1,” zastępuje się wyrazami „Hodowca, dostawca i użytkownik” , b) dodaje się ust. 2 w brzmieniu: „ 2. Hodowca, dostawca i użytkownik wyznaczają do uśmiercania zwierząt osobę, która: 1) ma wykształcenie co najmniej zasadnicze zawodowe, zasadnicze branżowe, średnie lub średnie branżowe; 2) odbyła szkolenie w zakresie metod uśmiercania zwierząt wykorzystywanych lub przeznaczonych do wykorzystania do celów naukowych lub edukacyjnych; 3) odbyła 3-miesięczną praktykę w zakresie wykonywania czynności związanych z uśmiercaniem zwierząt wykorzystywanych lub przeznaczonych do wykorzystania do celów naukowych lub edukacyjnych, pod nadzorem lekarza weterynarii lub osoby, która uśmierca te zwierzęta. ” ; 17) art. 21 otrzymuje brzmienie: „ Art. 21. 1. Użytkownik wyznacza osobę odpowiedzialną za planowanie procedur i doświadczeń oraz za ich przeprowadzanie, która ma wiedzę na temat gatunków zwierząt wykorzystywanych w tych procedurach i posiada co najmniej stopień naukowy doktora w zakresie nauk: 1) biologicznych, nauk farmaceutycznych, nauk medycznych, rolnictwa i ogrodnictwa, technologii żywności i żywienia, weterynarii lub zootechniki i rybactwa, ukończone szkolenie w zakresie przeprowadzania doświadczeń na zwierzętach oraz co najmniej 3-letni staż pracy umożliwiający uzyskanie praktycznych umiejętności w tym zakresie albo 2) innych niż wymienione w pkt 1 albo dyplom ukończenia studiów na kierunku w zakresie nauk wymienionych w pkt 1, ukończone studia podyplomowe lub szkolenie w zakresie przeprowadzania doświadczeń na zwierzętach oraz co najmniej 4-letni staż pracy umożliwiający uzyskanie praktycznych umiejętności w tym zakresie. 2. Użytkownik wyznacza do wykonywania procedur osobę, która posiada: 1) dyplom ukończenia studiów na kie"
    },
    {
      "provision_ref": "art2",
      "section": "2",
      "title": "Art. 2",
      "content": "Do dnia 10 listopada 2022 r. zwierzęta z rzędu naczelnych niestanowiące potomstwa zwierząt z rzędu naczelnych hodowanych w niewoli albo niepozyskiwane z kolonii samowystarczalnych, należące do gatunków wymienionych w załączniku nr II do dyrektywy Parlamentu Europejskiego i Rady 2010/63/UE z dnia 22 września 2010 r. w sprawie ochrony zwierząt wykorzystywanych do celów naukowych , z wyłączeniem marmozety zwyczajnej (Callithrix jacchus), są zwierzętami laboratoryjnymi w rozumieniu art. 2 ust. 1 pkt 2 ustawy zmienianej w art. 1."
    },
    {
      "provision_ref": "art3",
      "section": "3",
      "title": "Art. 3",
      "content": "Do postępowań w sprawach: 1) stwierdzania spełniania wymagań niezbędnych do prowadzenia działalności polegającej na hodowli, dostarczaniu zwierząt lub wykonywaniu procedur, o których mowa w art. 27 ust. 2 ustawy zmienianej w art. 1, 2) udzielania zgody na przeprowadzenie doświadczenia, o którym mowa w art. 36 ust. 1 pkt 1 lit. a ustawy zmienianej w art. 1, 3) udzielania zgody na zmianę doświadczenia, o którym mowa w art. 36 ust. 1 pkt 1 lit. b ustawy zmienianej w art. 1, 4) cofania udzielonej zgody na przeprowadzenie doświadczenia, o którym mowa w art. 36 ust. 1 pkt 2 ustawy zmienianej w art. 1 - wszczętych i niezakończonych przed dniem wejścia w życie niniejszej ustawy stosuje się przepisy dotychczasowe."
    },
    {
      "provision_ref": "art4",
      "section": "4",
      "title": "Art. 4",
      "content": "Do ocen retrospektywnych, o których mowa w art. 36 ust. 1 pkt 3 ustawy zmienianej w art. 1, rozpoczętych i niezakończonych przed dniem wejścia w życie niniejszej ustawy stosuje się przepisy dotychczasowe."
    },
    {
      "provision_ref": "art5",
      "section": "5",
      "title": "Art. 5",
      "content": "Wnioski o udostępnienie informacji publicznej złożone przed dniem wejścia w życie niniejszej ustawy rozpatruje się na podstawie przepisów ustawy zmienianej w art. 1, w brzmieniu nadanym niniejszą ustawą."
    },
    {
      "provision_ref": "art6",
      "section": "6",
      "title": "Art. 6",
      "content": "Z dniem wejścia w życie niniejszej ustawy zespoły doradcze do spraw dobrostanu zwierząt ustanowione na podstawie przepisów ustawy zmienianej w art. 1 stają się zespołami do spraw dobrostanu zwierząt w rozumieniu niniejszej ustawy."
    },
    {
      "provision_ref": "art7",
      "section": "7",
      "title": "Art. 7",
      "content": "Kadencja Krajowej Komisji Etycznej do Spraw Doświadczeń na Zwierzętach, o której mowa w art. 32 ust. 1 ustawy zmienianej w art. 1, rozpoczęta przed dniem wejścia w życie niniejszej ustawy trwa do dnia jej zakończenia."
    },
    {
      "provision_ref": "art8",
      "section": "8",
      "title": "Art. 8",
      "content": "Lokalne komisje etyczne do spraw doświadczeń na zwierzętach utworzone na podstawie art. 32 ust. 2 ustawy zmienianej w art. 1, w brzmieniu dotychczasowym, działają do dnia zakończenia ich kadencji."
    },
    {
      "provision_ref": "art9",
      "section": "9",
      "title": "Art. 9",
      "content": "Kadencji Krajowej Komisji Etycznej do Spraw Doświadczeń na Zwierzętach i kadencji lokalnych komisji etycznych do spraw doświadczeń na zwierzętach rozpoczętych przed dniem wejścia w życie niniejszej ustawy nie wlicza się do liczby kadencji, o której mowa w art. 34 ust. 4 ustawy zmienianej w art. 1."
    },
    {
      "provision_ref": "art10",
      "section": "10",
      "title": "Art. 10",
      "content": "Dokumentacja, o której mowa w art. 52 ust. 1 ustawy zmienianej w art. 1, dotycząca doświadczeń, na których przeprowadzenie uzyskano zgodę przed dniem wejścia w życie niniejszej ustawy, jest prowadzona i przechowywana na zasadach dotychczasowych."
    },
    {
      "provision_ref": "art11",
      "section": "11",
      "title": "Art. 11",
      "content": "1. Kontrole, o których mowa w art. 54 ust. 1 i 2 ustawy zmienianej w art. 1, wszczęte i niezakończone przed dniem wejścia w życie niniejszej ustawy, przeprowadza się na zasadach dotychczasowych. 2. Do eksperta biorącego udział w kontroli, o której mowa w art. 55 ust. 1 ustawy zmienianej w art. 1, wszczętej i niezakończonej do dnia wejścia w życie ustawy, stosuje się przepisy dotychczasowe."
    },
    {
      "provision_ref": "art12",
      "section": "12",
      "title": "Art. 12",
      "content": "Listę ekspertów biorących udział w przeprowadzaniu kontroli, o której mowa w art. 55 ust. 4 ustawy zmienianej w art. 1, w brzmieniu dotychczasowym, stosuje się do dnia udostępnienia przez ministra właściwego do spraw szkolnictwa wyższego i nauki w Biuletynie Informacji Publicznej na jego stronie podmiotowej listy, o której mowa w art. 55 ust. 6 ustawy zmienianej w art. 1."
    },
    {
      "provision_ref": "art13",
      "section": "13",
      "title": "Art. 13",
      "content": "Hodowcy i dostawcy w rozumieniu art. 2 ust. 1 pkt 9 i 10 ustawy zmienianej w art. 1 są obowiązani do spełnienia wymagań, o których mowa w art. 3b ust. 1 ustawy zmienianej w art. 1, nie później niż w terminie 3 miesięcy od dnia wejścia w życie niniejszej ustawy."
    },
    {
      "provision_ref": "art14",
      "section": "14",
      "title": "Art. 14",
      "content": "Hodowcy, dostawcy i użytkownicy w rozumieniu art. 2 ust. 1 pkt 9-11 ustawy zmienianej w art. 1 opracowują programy, o których mowa w art. 24a ustawy zmienianej w art. 1, w terminie 3 miesięcy od dnia wejścia w życie niniejszej ustawy."
    },
    {
      "provision_ref": "art15",
      "section": "15",
      "title": "Art. 15",
      "content": "Dotychczasowe przepisy wykonawcze wydane na podstawie art. 19, art. 22, art. 41 i art. 55 ust. 3 ustawy zmienianej w art. 1, zachowują moc do dnia wejścia w życie przepisów wykonawczych wydanych na podstawie art. 19, art. 22, art. 41 i art. 55 ust. 11 ustawy zmienianej w art. 1, w brzmieniu nadanym niniejszą ustawą, jednak nie dłużej niż przez 12 miesięcy od dnia wejścia w życie niniejszej ustawy."
    },
    {
      "provision_ref": "art16",
      "section": "16",
      "title": "Art. 16",
      "content": "Ustawa wchodzi w życie po upływie 14 dni od dnia ogłoszenia. 1) Niniejsza ustawa w zakresie swojej regulacji wdraża dyrektywę Parlamentu Europejskiego i Rady 2010/63/UE z dnia 22 września 2010 r. w sprawie ochrony zwierząt wykorzystywanych do celów naukowych (Dz. Urz. UE L 276 z 20.10.2010, str. 33 oraz Dz. Urz. UE L 170 z 25.06.2019, str. 115). 2) Zmiany wymienionej dyrektywy zostały ogłoszone w Dz. Urz. UE L 170 z 25.06.2019, str. 115. Pokaż całość var tree = [ { \"id\" : \"part_1\", \"title\" : \"Treść ustawy\", \"type\": \"part\", \"symbol\" : \"part_1\", \"children\" : [ {\"id\": \"arti_1\",\"symbol\": \"arti_1\",\"type\": \"arti\",\"name\": \"1\",\"title\": \"Art. 1.\",\"children\": [{\"id\": \"arti_1-pint_1\",\"symbol\": \"pint_1\",\"type\": \"pint\",\"name\": \"1\",\"title\": \"1)\",\"children\": [{\"id\": \"arti_1-pint_1-lett_a\",\"symbol\": \"lett_a\",\"type\": \"lett\",\"name\": \"a\",\"title\": \"a)\"},{\"id\": \"arti_1-pint_1-lett_b\",\"symbol\": \"lett_b\",\"type\": \"lett\",\"name\": \"b\",\"title\": \"b)\"}]},{\"id\": \"arti_1-pint_2\",\"symbol\": \"pint_2\",\"type\": \"pint\",\"name\": \"2\",\"title\": \"2)\"},{\"id\": \"arti_1-pint_3\",\"symbol\": \"pint_3\",\"type\": \"pint\",\"name\": \"3\",\"title\": \"3)\",\"children\": [{\"id\": \"arti_1-pint_3-lett_a\",\"symbol\": \"lett_a\",\"type\": \"lett\",\"name\": \"a\",\"title\": \"a)\"},{\"id\": \"arti_1-pint_3-lett_b\",\"symbol\": \"lett_b\",\"type\": \"lett\",\"name\": \"b\",\"title\": \"b)\"}]},{\"id\": \"arti_1-pint_4\",\"symbol\": \"pint_4\",\"type\": \"pint\",\"name\": \"4\",\"title\": \"4)\",\"children\": [{\"id\": \"arti_1-pint_4-lett_a\",\"symbol\": \"lett_a\",\"type\": \"lett\",\"name\": \"a\",\"title\": \"a)\"},{\"id\": \"arti_1-pint_4-lett_b\",\"symbol\": \"lett_b\",\"type\": \"lett\",\"name\": \"b\",\"title\": \"b)\"}]},{\"id\": \"arti_1-pint_5\",\"symbol\": \"pint_5\",\"type\": \"pint\",\"name\": \"5\",\"title\": \"5)\"},{\"id\": \"arti_1-pint_6\",\"symbol\": \"pint_6\",\"type\": \"pint\",\"name\": \"6\",\"title\": \"6)\",\"children\": [{\"id\": \"arti_1-pint_6-lett_a\",\"symbol\": \"lett_a\",\"type\": \"lett\",\"name\": \"a\",\"title\": \"a)\"},{\"id\": \"arti_1-pint_6-lett_b\",\"symbol\": \"lett_b\",\"type\": \"lett\",\"name\": \"b\",\"title\": \"b)\"}]},{\"id\": \"arti_1-pint_7\",\"symbol\": \"pint_7\",\"type\": \"pint\",\"name\": \"7\",\"title\": \"7)\",\"children\": [{\"id\": \"arti_1-pint_7-lett_a\",\"symbol\": \"lett_a\",\"type\": \"lett\",\"name\": \"a\",\"title\": \"a)\"},{\"id\": \"arti_1-pint_7-lett_b\",\"symbol\": \"lett_b\",\"type\": \"lett\",\"name\": \"b\",\"title\": \"b)\"}]},{\"id\": \"arti_1-pint_8\",\"symbol\": \"pint_8\",\"type\": \"pint\",\"name\": \"8\",\"title\": \"8)\"},{\"id\": \"arti_1-pint_9\",\"symbol\": \"pint_9\",\"type\": \"pint\",\"name\": \"9\",\"title\": \"9)\",\"children\": [{\"id\": \"arti_1-pint_9-lett_a\",\"symbol\": \"lett_a\",\"type\": \"lett\",\"name\": \"a\",\"title\": \"a)\"},{\"id\": \"arti_1-pint_9-lett_b\",\"symbol\": \"lett_b\",\"type\": \"lett\",\"name\": \"b\",\"title\": \"b)\"}]},{\"id\": \"arti_1-pint_10\",\"symbol\": \"pint_10\",\"type\": \"pint\",\"name\": \"10\",\"title\": \"10)\"},{\"id\": \"arti_1-pint_11\",\"symbol\": \"pint_11\",\"type\": \"pint\",\"name\": \"11\",\"title\": \"11)\"},{\"id\": \"arti_1-pint_12\",\"symbol\": \"pint_12\",\"type\": \"pint\",\"name\": \"12\",\"title\": \"12)\"},{\"id\": \"arti_1-pint_13\",\"symbol\": \"pint_13\",\"type\": \"pint\",\"name\": \"13\",\"title\": \"13)\"},{\"id\": \"arti_1-pint_14\",\"symbol\": \"pint_14\",\"type\": \"pint\",\"name\": \"14\",\"title\": \"14)\",\"children\": [{\"id\": \"arti_1-pint_14-lett_a\",\"symbol\": \"lett_a\",\"type\": \"lett\",\"name\": \"a\",\"title\": \"a)\"},{\"id\": \"arti_1-pint_14-lett_b\",\"symbol\": \"lett_b\",\"type\": \"lett\",\"name\": \"b\",\"title\": \"b)\"}]},{\"id\": \"arti_1-pint_15\",\"symbol\": \"pint_15\",\"type\": \"pint\",\"name\": \"15\",\"title\": \"15)\"},{\"id\": \"arti_1-pint_16\",\"symbol\": \"pint_16\",\"type\": \"pint\",\"name\": \"16\",\"title\": \"16)\",\"children\": [{\"id\": \"arti_1-pint_16-lett_a\",\"symbol\": \"lett_a\",\"type\": \"lett\",\"name\": \"a\",\"title\": \"a)\"},{\"id\": \"arti_1-pint_16-lett_b\",\"symbol\": \"lett_b\",\"type\": \"lett\",\"name\": \"b\",\"title\": \"b)\"}]},{\"id\": \"arti_1-pint_17\",\"symbol\": \"pint_17\",\"type\": \"pint\",\"name\": \"17\",\"title\": \"17)\"},{\"id\": \"arti_1-pint_18\",\"symbol\": \"pint_18\",\"type\": \"pint\",\"name\": \"18\",\"title\": \"18)\"},{\"id\": \"arti_1-pint_19\",\"symbol\": \"pint_19\",\"type\": \"pint\",\"name\": \"19\",\"title\": \"19)\"},{\"id\": \"arti_1-pint_20\",\"symbol\": \"pint_20\",\"type\": \"pint\",\"name\": \"20\",\"title\": \"20)\"},{\"id\": \"arti_1-pint_21\",\"symbol\": \"pint_21\",\"type\": \"pint\",\"name\": \"21\",\"title\": \"21)\"},{\"id\": \"arti_1-pint_22\",\"symbol\": \"pint_22\",\"type\": \"pint\",\"name\": \"22\",\"title\": \"22)\",\"children\": [{\"id\": \"arti_1-pint_22-lett_a\",\"symbol\": \"lett_a\",\"type\": \"lett\",\"name\": \"a\",\"title\": \"a)\"},{\"id\": \"arti_1-pint_22-lett_b\",\"symbol\": \"lett_b\",\"type\": \"lett\",\"name\": \"b\",\"title\": \"b)\"}]},{\"id\": \"arti_1-pint_23\",\"symbol\": \"pint_23\",\"type\": \"pint\",\"name\": \"23\",\"title\": \"23)\",\"children\": [{\"id\": \"arti_1-pint_23-lett_a\",\"symbol\": \"lett_a\",\"type\": \"lett\",\"name\": \"a\",\"title\": \"a)\"},{\"id\": \"arti_1-pint_23-lett_b\",\"symbol\": \"lett_b\",\"type\": \"lett\",\"name\": \"b\",\"title\": \"b)\"}]},{\"id\": \"arti_1-pint_24\",\"symbol\": \"pint_24\",\"type\": \"pint\",\"name\": \"24\",\"title\": \"24)\"},{\"id\": \"arti_1-pint_25\",\"symbol\": \"pint_25\",\"type\": \"pint\",\"name\": \"25\",\"title\": \"25)\",\"children\": [{\"id\": \"arti_1-pint_25-lett_a\",\"symbol\": \"lett_a\",\"type\": \"lett\",\"name\": \"a\",\"title\": \"a)\"},{\"id\": \"arti_1-pint_25-lett_b\",\"symbol\": \"lett_b\",\"type\": \"lett\",\"name\": \"b\",\"title\": \"b)\"},{\"id\": \"arti_1-pint_25-lett_c\",\"symbol\": \"lett_c\",\"type\": \"lett\",\"name\": \"c\",\"title\": \"c)\"}]},{\"id\": \"arti_1-pint_26\",\"symbol\": \"pint_26\",\"type\": \"pint\",\"name\": \"26\",\"title\": \"26)\"},{\"id\": \"arti_1-pint_27\",\"symbol\": \"pint_27\",\"type\": \"pint\",\"name\": \"27\",\"title\": \"27)\"},{\"id\": \"arti_1-pint_28\",\"symbol\": \"pint_28\",\"type\": \"pint\",\"name\": \"28\",\"title\": \"28)\",\"children\": [{\"id\": \"arti_1-pint_28-lett_a\",\"symbol\": \"lett_a\",\"type\": \"lett\",\"name\": \"a\",\"title\": \"a)\"},{\"id\": \"arti_1-pint_28-lett_b\",\"symbol\": \"lett_b\",\"type\": \"lett\",\"name\": \"b\",\"title\": \"b)\"},{\"id\": \"arti_1-pint_28-lett_c\",\"symbol\": \"lett_c\",\"type\": \"lett\",\"name\": \"c\",\"title\": \"c)\"},{\"id\": \"arti_1-pint_28-lett_d\",\"symbol\": \"lett_d\",\"type\": \"lett\",\"name\": \"d\",\"title\": \"d)\"},{\"id\": \"arti_1-pint_28-lett_e\",\"symbol\": \"lett_e\",\"type\": \"lett\",\"name\": \"e\",\"title\": \"e)\"}]},{\"id\": \"arti_1-pint_29\",\"symbol\": \"pint_29\",\"type\": \"pint\",\"name\": \"29\",\"title\": \"29)\",\"children\": [{\"id\": \"arti_1-pint_29-lett_a\",\"symbol\": \"lett_a\",\"type\": \"lett\",\"name\": \"a\",\"title\": \"a)\"},{\"id\": \"arti_1-pint_29-lett_b\",\"symbol\": \"lett_b\",\"type\": \"lett\",\"name\": \"b\",\"title\": \"b)\"},{\"id\": \"arti_1-pint_29-lett_c\",\"symbol\": \"lett_c\",\"type\": \"lett\",\"name\": \"c\",\"title\": \"c)\"},{\"id\": \"arti_1-pint_29-lett_d\",\"symbol\": \"lett_d\",\"type\": \"lett\",\"name\": \"d\",\"title\": \"d)\"}]},{\"id\": \"arti_1-pint_30\",\"symbol\": \"pint_30\",\"type\": \"pint\",\"name\": \"30\",\"title\": \"30)\"},{\"id\": \"arti_1-pint_31\",\"symbol\": \"pint_31\",\"type\": \"pint\",\"name\": \"31\",\"title\": \"31)\",\"children\": [{\"id\": \"arti_1-pint_31-lett_a\",\"symbol\": \"lett_a\",\"type\": \"lett\",\"name\": \"a\",\"title\": \"a)\"},{\"id\": \"arti_1-pint_31-lett_b\",\"symbol\": \"lett_b\",\"type\": \"lett\",\"name\": \"b\",\"title\": \"b)\"},{\"id\": \"arti_1-pint_31-lett_c\",\"symbol\": \"lett_c\",\"type\": \"lett\",\"name\": \"c\",\"title\": \"c)\"},{\"id\": \"arti_1-pint_31-lett_d\",\"symbol\": \"lett_d\",\"type\": \"lett\",\"name\": \"d\",\"title\": \"d)\"}]},{\"id\": \"arti_1-pint_32\",\"symbol\": \"pint_32\",\"type\": \"pint\",\"name\": \"32\",\"title\": \"32)\",\"children\": [{\"id\": \"arti_1-pint_32-lett_a\",\"symbol\": \"lett_a\",\"type\": \"lett\",\"name\": \"a\",\"title\": \"a)\"},{\"id\": \"arti_1-pint_32-lett_b\",\"symbol\": \"lett_b\",\"type\": \"lett\",\"name\": \"b\",\"title\": \"b)\"}]},{\"id\": \"arti_1-pint_33\",\"symbol\": \"pint_33\",\"type\": \"pint\",\"name\": \"33\",\"title\": \"33)\"},{\"id\": \"arti_1-pint_34\",\"symbol\": \"pint_34\",\"type\": \"pint\",\"name\": \"34\",\"title\": \"34)\"},{\"id\": \"arti_1-pint_35\",\"symbol\": \"pint_35\",\"type\": \"pint\",\"name\": \"35\",\"title\": \"35)\",\"children\": [{\"id\": \"arti_1-pint_35-lett_a\",\"symbol\": \"lett_a\",\"type\": \"lett\",\"name\": \"a\",\"title\": \"a)\"},{\"id\": \"arti_1-pint_35-lett_b\",\"symbol\": \"lett_b\",\"type\": \"lett\",\"name\": \"b\",\"title\": \"b)\"}]},{\"id\": \"arti_1-pint_36\",\"symbol\": \"pint_36\",\"type\": \"pint\",\"name\": \"36\",\"title\": \"36)\"},{\"id\": \"arti_1-pint_37\",\"symbol\": \"pint_37\",\"type\": \"pint\",\"name\": \"37\",\"title\": \"37)\"},{\"id\": \"arti_1-pint_38\",\"symbol\": \"pint_38\",\"type\": \"pint\",\"name\": \"38\",\"title\": \"38)\",\"children\": [{\"id\": \"arti_1-pint_38-lett_a\",\"symbol\": \"lett_a\",\"type\": \"lett\",\"name\": \"a\",\"title\": \"a)\"},{\"id\": \"arti_1-pint_38-lett_b\",\"symbol\": \"lett_b\",\"type\": \"lett\",\"name\": \"b\",\"title\": \"b)\"}]},{\"id\": \"arti_1-pint_39\",\"symbol\": \"pint_39\",\"type\": \"pint\",\"name\": \"39\",\"title\": \"39)\",\"children\": [{\"id\": \"arti_1-pint_39-lett_a\",\"symbol\": \"lett_a\",\"type\": \"lett\",\"name\": \"a\",\"title\": \"a)\"},{\"id\": \"arti_1-pint_39-lett_b\",\"symbol\": \"lett_b\",\"type\": \"lett\",\"name\": \"b\",\"title\": \"b)\"}]},{\"id\": \"arti_1-pint_40\",\"symbol\": \"pint_40\",\"type\": \"pint\",\"name\": \"40\",\"title\": \"40)\"},{\"id\": \"arti_1-pint_41\",\"symbol\": \"pint_41\",\"type\": \"pint\",\"name\": \"41\",\"title\": \"41)\"},{\"id\": \"arti_1-pint_42\",\"symbol\": \"pint_42\",\"type\": \"pint\",\"name\": \"42\",\"title\": \"42)\",\"children\": [{\"id\": \"arti_1-pint_42-lett_a\",\"symbol\": \"lett_a\",\"type\": \"lett\",\"name\": \"a\",\"title\": \"a)\"},{\"id\": \"arti_1-pint_42-lett_b\",\"symbol\": \"lett_b\",\"type\": \"lett\",\"name\": \"b\",\"title\": \"b)\"},{\"id\": \"arti_1-pint_42-lett_c\",\"symbol\": \"lett_c\",\"type\": \"lett\",\"name\": \"c\",\"title\": \"c)\"}]},{\"id\": \"arti_1-pint_43\",\"symbol\": \"pint_43\",\"type\": \"pint\",\"name\": \"43\",\"title\": \"43)\"},{\"id\": \"arti_1-pint_44\",\"symbol\": \"pint_44\",\"type\": \"pint\",\"name\": \"44\",\"title\": \"44)\",\"children\": [{\"id\": \"arti_1-pint_44-lett_a\",\"symbol\": \"lett_a\",\"type\": \"lett\",\"name\": \"a\",\"title\": \"a)\"},{\"id\": \"arti_1-pint_44-lett_b\",\"symbol\": \"lett_b\",\"type\": \"lett\",\"name\": \"b\",\"title\": \"b)\"}]},{\"id\": \"arti_1-pint_45\",\"symbol\": \"pint_45\",\"type\": \"pint\",\"name\": \"45\",\"title\": \"45)\"},{\"id\": \"arti_1-pint_46\",\"symbol\": \"pint_46\",\"type\": \"pint\",\"name\": \"46\",\"title\": \"46)\"},{\"id\": \"arti_1-pint_47\",\"symbol\": \"pint_47\",\"type\": \"pint\",\"name\": \"47\",\"title\": \"47)\"},{\"id\": \"arti_1-pint_48\",\"symbol\": \"pint_48\",\"type\": \"pint\",\"name\": \"48\",\"title\": \"48)\",\"children\": [{\"id\": \"arti_1-pint_48-lett_a\",\"symbol\": \"lett_a\",\"type\": \"lett\",\"name\": \"a\",\"title\": \"a)\"},{\"id\": \"arti_1-pint_48-lett_b\",\"symbol\": \"lett_b\",\"type\": \"lett\",\"name\": \"b\",\"title\": \"b)\"},{\"id\": \"arti_1-pint_48-lett_c\",\"symbol\": \"lett_c\",\"type\": \"lett\",\"name\": \"c\",\"title\": \"c)\"}]},{\"id\": \"arti_1-pint_49\",\"symbol\": \"pint_49\",\"type\": \"pint\",\"name\": \"49\",\"title\": \"49)\",\"children\": [{\"id\": \"arti_1-pint_49-lett_a\",\"symbol\": \"lett_a\",\"type\": \"lett\",\"name\": \"a\",\"title\": \"a)\"},{\"id\": \"arti_1-pint_49-lett_b\",\"symbol\": \"lett_b\",\"type\": \"lett\",\"name\": \"b\",\"title\": \"b)\"}]},{\"id\": \"arti_1-pint_50\",\"symbol\": \"pint_50\",\"type\": \"pint\",\"name\": \"50\",\"title\": \"50)\"},{\"id\": \"arti_1-pint_51\",\"symbol\": \"pint_51\",\"type\": \"pint\",\"name\": \"51\",\"title\": \"51)\"},{\"id\": \"arti_1-pint_52\",\"symbol\": \"pint_52\",\"type\": \"pint\",\"name\": \"52\",\"title\": \"52)\"},{\"id\": \"arti_1-pint_53\",\"symbol\": \"pint_53\",\"type\": \"pint\",\"name\": \"53\",\"title\": \"53)\"},{\"id\": \"arti_1-pint_54\",\"symbol\": \"pint_54\",\"type\": \"pint\",\"name\": \"54\",\"title\": \"54)\"},{\"id\": \"arti_1-pint_55\",\"symbol\": \"pint_55\",\"type\": \"pint\",\"name\": \"55\",\"title\": \"55)\"},{\"id\": \"arti_1-pint_56\",\"symbol\": \"pint_56\",\"type\": \"pint\",\"name\": \"56\",\"title\": \"56)\",\"children\": [{\"id\": \"arti_1-pint_56-lett_a\",\"symbol\": \"lett_a\",\"type\": \"lett\",\"name\": \"a\",\"title\": \"a)\"},{\"id\": \"arti_1-pint_56-lett_b\",\"symbol\": \"lett_b\",\"type\": \"lett\",\"name\": \"b\",\"title\": \"b)\"}]},{\"id\": \"arti_1-pint_57\",\"symbol\": \"pint_57\",\"type\": \"pint\",\"name\": \"57\",\"title\": \"57)\"},{\"id\": \"arti_1-pint_58\",\"symbol\": \"pint_58\",\"type\": \"pint\",\"name\": \"58\",\"title\": \"58)\"}]},{\"id\": \"arti_2\",\"symbol\": \"arti_2\",\"type\": \"arti\",\"name\": \"2\",\"title\": \"Art. 2.\"},{\"id\": \"arti_3\",\"symbol\": \"arti_3\",\"type\": \"arti\",\"name\": \"3\",\"title\": \"Art. 3.\",\"children\": [{\"id\": \"arti_3-pint_1\",\"symbol\": \"pint_1\",\"type\": \"pint\",\"name\": \"1\",\"title\": \"1)\"},{\"id\": \"arti_3-pint_2\",\"symbol\": \"pint_2\",\"type\": \"pint\",\"name\": \"2\",\"title\": \"2)\"},{\"id\": \"arti_3-pint_3\",\"symbol\": \"pint_3\",\"type\": \"pint\",\"name\": \"3\",\"title\": \"3)\"},{\"id\": \"arti_3-pint_4\",\"symbol\": \"pint_4\",\"type\": \"pint\",\"name\": \"4\",\"title\": \"4)\"}]},{\"id\": \"arti_4\",\"symbol\": \"arti_4\",\"type\": \"arti\",\"name\": \"4\",\"title\": \"Art. 4.\"},{\"id\": \"arti_5\",\"symbol\": \"arti_5\",\"type\": \"arti\",\"name\": \"5\",\"title\": \"Art. 5.\"},{\"id\": \"arti_6\",\"symbol\": \"arti_6\",\"type\": \"arti\",\"name\": \"6\",\"title\": \"Art. 6.\"},{\"id\": \"arti_7\",\"symbol\": \"arti_7\",\"type\": \"arti\""
    }
  ],
  "definitions": [
    {
      "term": "w art. 2: a) w ust. 1:",
      "definition": "w pkt 2: - - w lit. a wyrazy „świnka morska” zastępuje się wyrazami „kawia domowa” , - - w lit. b po wyrazach „w niewoli” dodaje się wyrazy „albo pozyskiwane z kolonii samowystarczalnych” , - - uchyla się lit. c, - pkt 9 otrzymuje brzmienie: „ 9) hodowca - osobę fizyczną, osobę prawną lub jednostkę organizacyjną nieposiadającą osobowości prawnej, która hoduje zwierzęta laboratoryjne w celu wykorzystania ich w procedurach lub aby wykorzystać ich narządy lub tkanki do celów określonych w art. 3 lub która hoduje inne zwierzęta głównie w tych celach; ” , - w pkt 11: - - po wyrazach „w procedurach” dodaje się wyrazy „lub uśmierca zwierzęta, aby wykorzystać ich narządy lub tkanki do celów określonych w art. 3” , - - kropkę zastępuje się średnikiem i dodaje się pkt 12 w brzmieniu: „ 12) kolonia samowystarczalna - kolonię, w której zwierzęta z rzędu naczelnych są hodowane wyłącznie w ramach kolonii lub są pozyskiwane z innych kolonii, ale nie są zwierzętami dzikimi, oraz w której zwierzęta są utrzymywane w sposób zapewniający ich przyzwyczajenie do ludzi. ” , b) uchyla się ust. 3",
      "source_provision": "art1"
    }
  ]
}