{
  "id": "pl-du-2011-660",
  "type": "statute",
  "title": "Ustawa z dnia 28 kwietnia 2011 r. o zmianie ustawy o prawach pacjenta i Rzeczniku Praw Pacjenta oraz ustawy o ubezpieczeniach obowiązkowych, Ubezpieczeniowym Funduszu Gwarancyjnym i Polskim Biurze Ubezpieczycieli Komunikacyjnych",
  "title_en": "",
  "short_name": "pl-du-2011-660",
  "status": "in_force",
  "issued_date": "2011-04-28",
  "in_force_date": "2011-06-02",
  "url": "https://api.sejm.gov.pl/eli/acts/DU/2011/660",
  "provisions": [
    {
      "provision_ref": "art1",
      "section": "1",
      "title": "Art. 1",
      "content": "W ustawie z dnia 6 listopada 2008 r. o prawach pacjenta i Rzeczniku Praw Pacjenta ( Dz. U. z 2009 r. Nr 52, poz. 417 i Nr 76, poz. 641 , z 2010 r. Nr 96, poz. 620 oraz z 2011 r. Nr 112, poz. 654 ) wprowadza się następujące zmiany: 1) w art. 1 w pkt 5 kropkę zastępuje się średnikiem i dodaje pkt 6 w brzmieniu: „ 6) zasady i tryb ustalania odszkodowania i zadośćuczynienia w przypadku zdarzeń medycznych. ” ; 2) w art. 14: a) po ust. 2 dodaje się ust. 2a w brzmieniu: „ 2a. Przepisu ust. 1 nie stosuje się także do postępowania przed wojewódzką komisją do spraw orzekania o zdarzeniach medycznych, o której mowa w art. 67e ust. 1. ” , b) ust. 3 otrzymuje brzmienie: „ 3. Osoby wykonujące zawód medyczny, z wyjątkiem przypadków, o których mowa w ust. 2 pkt 1 -3 i ust. 2a, są związane tajemnicą również po śmierci pacjenta. ” ; 3) w art. 26 w ust. 3 w pkt 8 kropkę zastępuje się średnikiem i dodaje pkt 9 i 10 w brzmieniu: „ 9) wojewódzkiej komisji do spraw orzekania o zdarzeniach medycznych, o której mowa w art. 67e ust. 1, w zakresie prowadzonego postępowania; 10) spadkobiercom w zakresie prowadzonego postępowania przed wojewódzką komisją do spraw orzekania o zdarzeniach medycznych, o której mowa w art. 67e ust. 1. ” ; 4) w art. 28 po ust. 2 dodaje się ust. 2a w brzmieniu: „ 2a. Opłaty, o której mowa w ust. 1, nie pobiera się w przypadku udostępniania dokumentacji medycznej w związku z postępowaniem przed wojewódzką komisją do spraw orzekania o zdarzeniach medycznych, o której mowa w art. 67e ust. 1. ” ; 5) po rozdziale 13 dodaje się rozdział 13a w brzmieniu: „ Rozdział 13a Zasady i tryb ustalania odszkodowania i zadośćuczynienia w przypadku zdarzeń medycznych Art. 67a. 1. Przepisy niniejszego rozdziału stosuje się do zakażenia pacjenta biologicznym czynnikiem chorobotwórczym, uszkodzenia ciała lub rozstroju zdrowia pacjenta albo śmierci pacjenta będącego następstwem niezgodnych z aktualną wiedzą medyczną: 1) diagnozy, jeżeli spowodowała ona niewłaściwe leczenie albo opóźniła właściwe leczenie, przyczyniając się do rozwoju choroby, 2) leczenia, w tym wykonania zabiegu operacyjnego, 3) zastosowania produktu leczniczego lub wyrobu medycznego - zwanego dalej „zdarzeniem medycznym”. 2. Przepisy niniejszego rozdziału stosuje się do zdarzeń medycznych będących następstwem udzielania świadczeń zdrowotnych w szpitalu w rozumieniu przepisów o działalności leczniczej. Art. 67b. 1. W przypadku: 1) zakażenia, uszkodzenia ciała lub rozstroju zdrowia, o których mowa w art. 67a ust. 1 - pacjent lub jego przedstawiciel ustawowy mogą wystąpić z wnioskiem o ustalenie zdarzenia medycznego, 2) śmierci, o której mowa w art. 67a ust. 1 - wniosek o ustalenie zdarzenia medycznego mogą złożyć spadkobiercy pacjenta - zwani dalej „podmiotami składającymi wniosek”. 2. Postępowanie przed wojewódzką komisją do spraw orzekania o zdarzeniach medycznych, o której mowa w art. 67e ust. 1: 1) zawiesza się w przypadku toczącego się w związku z tym samym zdarzeniem postępowania w przedmiocie odpowiedzialności zawodowej osoby wykonującej zawód medyczny lub postępowania karnego w sprawie o przestępstwo; 2) nie wszczyna się, a wszczęte umarza w przypadku, gdy w związku z tym samym zdarzeniem prawomocnie osądzono sprawę o odszkodowanie lub zadośćuczynienie pieniężne albo toczy się postępowanie cywilne w tej sprawie. 3. W przypadku zakończenia postępowania, o którym mowa w ust. 2 pkt 1, postępowanie przed wojewódzką komisją do spraw orzekania o zdarzeniach medycznych, o której mowa w art. 67e ust. 1, podejmuje się z urzędu. Art. 67c. 1. Wniosek o ustalenie zdarzenia medycznego, zwany dalej „wnioskiem”, wnosi się do wojewódzkiej komisji do spraw orzekania o zdarzeniach medycznych właściwej ze względu na siedzibę szpitala. 2. Wniosek wnosi się w terminie 1 roku od dnia, w którym podmiot składający wniosek dowiedział się o zakażeniu, uszkodzeniu ciała lub rozstroju zdrowia albo nastąpiła śmierć pacjenta, o których mowa w art. 67a ust. 1, jednakże termin ten nie może być dłuższy niż 3 lata od dnia, w którym nastąpiło zdarzenie skutkujące zakażeniem, uszkodzeniem ciała lub rozstrojem zdrowia albo śmiercią pacjenta. 3. Złożenie wniosku, w wyniku którego wojewódzka komisja do spraw orzekania o zdarzeniach medycznych, o której mowa w art. 67e ust. 1, wydała orzeczenie o zdarzeniu medycznym, przerywa bieg terminu przedawnienia roszczeń określony w przepisach Kodeksu cywilnego wynikający ze zdarzeń objętych wnioskiem. 4. W przypadku śmierci pacjenta, o której mowa w art. 67a ust. 1, termin, o którym mowa w ust. 2, nie biegnie do dnia zakończenia postępowania spadkowego. Art. 67d. 1. Wniosek zawiera: 1) dane pacjenta: a) imię i nazwisko, b) datę urodzenia, c) numer PESEL albo serię i numer dokumentu stwierdzającego tożsamość, jeżeli posiada; 2) imię i nazwisko przedstawiciela ustawowego, jeżeli dotyczy; 3) imiona i nazwiska wszystkich spadkobierców, jeżeli dotyczy; 4) wskazanie, który ze spadkobierców reprezentuje pozostałych w postępowaniu przed wojewódzką komisją do spraw orzekania o zdarzeniach medycznych, o której mowa w art. 67e ust. 1, jeżeli dotyczy; 5) adres do doręczeń; 6) dane podmiotu leczniczego prowadzącego szpital: a) firmę, b) adres siedziby oraz adres szpitala, jeżeli dotyczy; 7) uzasadnienie wniosku zawierające uprawdopodobnienie zdarzenia, którego następstwem było zakażenie, uszkodzenie ciała, rozstrój zdrowia albo śmierć pacjenta, o których mowa w art. 67a ust. 1, oraz szkody majątkowej lub niemajątkowej; 8) wskazanie, czy przedmiotem wniosku jest zakażenie, uszkodzenie ciała, rozstrój zdrowia albo śmierć pacjenta, o których mowa w art. 67a ust. 1; 9) propozycję wysokości odszkodowania i zadośćuczynienia, nie wyższą niż określona w art. 67k ust. 7. 2. Do wniosku dołącza się: 1) dowody uprawdopodabniające okoliczności wskazane we wniosku; 2) potwierdzenie uiszczenia opłaty, o której mowa w ust. 3; 3) postanowienie o stwierdzeniu nabycia spadku w przypadku, o którym mowa w art. 67b ust. 1 pkt 2, oraz pełnomocnictwo do reprezentowania pozostałych spadkobierców, w przypadku złożenia wniosku przez co najmniej jednego z nich. 3. Złożenie wniosku podlega opłacie w wysokości 200 zł. Opłata podlega zaliczeniu na poczet kosztów postępowania przed wojewódzką komisją do spraw orzekania o zdarzeniach medycznych. 4. Opłatę, o której mowa w ust. 3, uiszcza się na rachunek właściwego urzędu wojewódzkiego. 5. Wniosek niekompletny lub nienależycie opłacony jest zwracany bez rozpatrzenia podmiotowi składającemu wniosek. 6. Kompletny i należycie opłacony wniosek wojewódzka komisja do spraw orzekania o zdarzeniach medycznych, o której mowa w art. 67e ust. 1, przekazuje niezwłocznie kierownikowi podmiotu leczniczego prowadzącego szpital, z działalnością którego wiąże się wniosek, oraz ubezpieczycielowi, o którym mowa w art. 67i ust. 2 pkt 2. Kierownik tego podmiotu i ubezpieczyciel przedstawiają stanowisko w terminie 30 dni od dnia otrzymania wniosku wraz z dowodami na poparcie swojego stanowiska. Nieprzedstawienie stanowiska jest równoznaczne z akceptacją wniosku w zakresie dotyczącym okoliczności w nim wskazanych oraz proponowanej wysokości odszkodowania i zadośćuczynienia. Art. 67e. 1. Tworzy się wojewódzkie komisje do spraw orzekania o zdarzeniach medycznych, zwane dalej „wojewódzkimi komisjami”. Siedzibą wojewódzkiej komisji jest siedziba właściwego urzędu wojewódzkiego. 2. Wykonywanie zadań wojewódzkiej komisji nie stanowi wykonywania władzy publicznej. 3. W skład wojewódzkiej komisji wchodzi 16 członków, w tym: 1) 8 członków posiadających co najmniej wyższe wykształcenie i tytuł magistra lub równorzędny w dziedzinie nauk medycznych, którzy wykonują zawód medyczny przez okres co najmniej 5 lat albo posiadają stopień naukowy doktora w dziedzinie nauk medycznych, 2) 8 członków posiadających co najmniej wyższe wykształcenie i tytuł magistra w dziedzinie nauk prawnych, którzy przez okres co najmniej 5 lat byli zatrudnieni na stanowiskach związanych ze stosowaniem lub tworzeniem prawa albo posiadają stopień naukowy doktora w dziedzinie nauk prawnych - którzy posiadają wiedzę w zakresie praw pacjenta oraz korzystają z pełni praw publicznych. 4. Członkiem wojewódzkiej komisji nie może być osoba: 1) prawomocnie skazana za umyślne przestępstwo lub umyślne przestępstwo skarbowe; 2) prawomocnie ukarana karą z tytułu odpowiedzialności dyscyplinarnej albo zawodowej; 3) wobec której prawomocnie orzeczono środek karny określony w art. 39 pkt 2 lub 2a Kodeksu karnego . 5. Spośród członków wojewódzkiej komisji: 1) 14 członków powołuje wojewoda, przy czym: a) 4 członków stanowią osoby powołane spośród kandydatów zgłoszonych przez samorządy zawodowe lekarzy, lekarzy dentystów, pielęgniarek i położnych oraz diagnostów laboratoryjnych, mających siedzibę na terenie województwa, b) 4 członków stanowią osoby powołane spośród kandydatów zgłoszonych przez samorząd zawodowy adwokatury oraz samorząd radców prawnych, mających siedzibę na terenie województwa, c) 6 członków stanowią osoby powołane spośród kandydatów zgłoszonych przez organizacje społeczne działające na terenie województwa na rzecz praw pacjenta; 2) po jednym członku powołuje minister właściwy do spraw zdrowia i Rzecznik Praw Pacjenta. 6. Podmioty, o których mowa w ust. 5 pkt 1, zgłaszają, a minister właściwy do spraw zdrowia i Rzecznik Praw Pacjenta powołują, kandydatów na członków wojewódzkiej komisji nie później niż na 6 miesięcy przed upływem kadencji wojewódzkiej komisji, a w przypadku odwołania członka wojewódzkiej komisji przed upływem kadencji - w terminie wyznaczonym przez wojewodę. 7. Kadencja wojewódzkiej komisji wynosi 6 lat. W przypadku gdy członek wojewódzkiej komisji zostanie odwołany przed upływem kadencji na podstawie ust. 9, kadencja członka powołanego na jego miejsce upływa z dniem upływu kadencji wojewódzkiej komisji. 8. Przepisy ust. 6 i 7 stosuje się odpowiednio w przypadku śmierci członka wojewódzkiej komisji. 9. Członka wojewódzkiej komisji odwołuje, przed upływem kadencji, organ, który go powołał, w przypadku: 1) złożenia rezygnacji ze stanowiska; 2) choroby trwale uniemożliwiającej wykonywanie powierzonych zadań; 3) zaistnienia okoliczności określonych w art. 67g ust. 1; 4) niezłożenia oświadczenia, o którym mowa w art. 67g ust. 4; 5) zaistnienia okoliczności określonych w ust. 4; 6) uchylania się od wykonywania obowiązków członka wojewódzkiej komisji albo ich nieprawidłowego wykonywania. 10. O powołaniu na członka wojewódzkiej komisji oraz o terminach jej posiedzeń informuje się pracodawcę tej osoby. 11. Pracami wojewódzkiej komisji kieruje przewodniczący wybrany spośród jej członków na pierwszym posiedzeniu większością głosów przy obecności co najmniej 3/4 jej członków, w głosowaniu tajnym. 12. Termin pierwszego posiedzenia wojewódzkiej komisji wyznacza wojewoda. Pierwszemu posiedzeniu, do czasu wyboru przewodniczącego, o którym mowa w ust. 11, przewodniczy członek wojewódzkiej komisji wyznaczony przez wojewodę. 13. Wojewódzka komisja działa na podstawie uchwalonego przez siebie regulaminu, przy czym: 1) uchwały wojewódzkiej komisji są podejmowane zwykłą większością głosów, chyba że ustawa stanowi inaczej; 2) w przypadku równej liczby głosów rozstrzyga głos przewodniczącego; 3) członek wojewódzkiej komisji nie może wstrzymać się od głosu; 4) wojewódzka komisja działa na posiedzeniach, które są protokołowane. Art. 67f. 1. Wojewódzkie komisje orzekają w składzie 4-osobowym. 2. Skład orzekający wojewódzkiej komisji, zwany dalej „składem orzekającym”, jest wyznaczany przez przewodniczącego wojewódzkiej komisji według kolejności wpływu wniosków o ustalenie zdarzenia medycznego z alfabetycznej listy członków wojewódzkiej komisji, przy czym 2 członków składu orzekającego spełnia wymagania, o których mowa w art. 67e ust. 3 pkt 1, a 2 członków składu orzekającego spełnia wymagania, o których mowa w art. 67e ust. 3 pkt 2. Odstępstwo od tej kolejności jest dopuszczalne tylko z przyczyn określonych w art. 67g ust. 2. 3. Pracami składu orzekającego kieruje przewodniczący. Termin pie"
    },
    {
      "provision_ref": "art2",
      "section": "2",
      "title": "Art. 2",
      "content": "W ustawie z dnia 22 maja 2003 r. o ubezpieczeniach obowiązkowych, Ubezpieczeniowym Funduszu Gwarancyjnym i Polskim Biurze Ubezpieczycieli Komunikacyjnych ( Dz. U. Nr 124, poz. 1152 , z późn. zm. 1) Zmiany wymienionej ustawy zostały ogłoszone w Dz. U. z 2004 r. Nr 26, poz. 225, Nr 96, poz. 959, Nr 141, poz. 1492, Nr 273, poz. 2703 i Nr 281, poz. 2778, z 2005 r. Nr 167, poz. 1396, z 2006 r. Nr 157, poz. 1119, z 2007 r. Nr 49, poz. 328, Nr 82, poz. 557, Nr 102, poz. 691 i Nr 133, poz. 922, z 2008 r. Nr 225, poz. 1486, z 2009 r. Nr 91, poz. 739 i Nr 97, poz. 802, z 2010 r. Nr 28, poz. 145 i Nr 43, poz. 246 oraz z 2011 r. Nr 80, poz. 432. ) w art. 13 ust. 1 otrzymuje brzmienie: „ 1. Zakład ubezpieczeń wypłaca odszkodowanie lub świadczenie z tytułu ubezpieczenia obowiązkowego na podstawie uznania roszczenia uprawnionego z umowy ubezpieczenia w wyniku ustaleń, zawartej z nim ugody, prawomocnego orzeczenia sądu lub w sposób określony w przepisach ustawy z dnia 6 listopada 2008 r. o prawach pacjenta i Rzeczniku Praw Pacjenta ( Dz. U. z 2009 r. Nr 52, poz. 417 , z późn. zm. 2) Zmiany wymienionej ustawy zostały ogłoszone w Dz. U. z 2009 r. Nr 76, poz. 641, z 2010 r. Nr 96, poz. 620 oraz z 2011 r. Nr 112, poz. 654 i Nr 113, poz. 660. ) . ” ."
    },
    {
      "provision_ref": "art3",
      "section": "3",
      "title": "Art. 3",
      "content": "1. Samorządy zawodowe lekarzy, lekarzy dentystów, pielęgniarek i położnych, diagnostów laboratoryjnych, adwokatury oraz radców prawnych oraz organizacje społeczne działające na terenie województwa na rzecz praw pacjenta zgłoszą kandydatów na członków wojewódzkiej komisji do spraw orzekania o zdarzeniach medycznych pierwszej kadencji nie później niż w terminie do dnia 30 września 2011 r. 2. Minister właściwy do spraw zdrowia i Rzecznik Praw Pacjenta powołają członków wojewódzkiej komisji do spraw orzekania o zdarzeniach medycznych pierwszej kadencji nie później niż w terminie do dnia 30 listopada 2011 r. 3. Wojewodowie powołają członków wojewódzkiej komisji do spraw orzekania o zdarzeniach medycznych pierwszej kadencji nie później niż w terminie do dnia 31 grudnia 2011 r."
    },
    {
      "provision_ref": "art4",
      "section": "4",
      "title": "Art. 4",
      "content": "Przepisy ustawy stosuje się do zdarzeń, których skutkiem jest zakażenie pacjenta biologicznym czynnikiem chorobotwórczym, uszkodzenie ciała lub rozstrój zdrowia pacjenta albo śmierć pacjenta, mających miejsce po dniu wejścia w życie ustawy."
    },
    {
      "provision_ref": "art5",
      "section": "5",
      "title": "Art. 5",
      "content": "Ustawa wchodzi w życie z dniem 1 stycznia 2012 r., z wyjątkiem art. 3, który wchodzi w życie po upływie 14 dni od dnia ogłoszenia. 1) Zmiany wymienionej ustawy zostały ogłoszone w Dz. U. z 2004 r. Nr 26, poz. 225, Nr 96, poz. 959, Nr 141, poz. 1492, Nr 273, poz. 2703 i Nr 281, poz. 2778, z 2005 r. Nr 167, poz. 1396, z 2006 r. Nr 157, poz. 1119, z 2007 r. Nr 49, poz. 328, Nr 82, poz. 557, Nr 102, poz. 691 i Nr 133, poz. 922, z 2008 r. Nr 225, poz. 1486, z 2009 r. Nr 91, poz. 739 i Nr 97, poz. 802, z 2010 r. Nr 28, poz. 145 i Nr 43, poz. 246 oraz z 2011 r. Nr 80, poz. 432. 2) Zmiany wymienionej ustawy zostały ogłoszone w Dz. U. z 2009 r. Nr 76, poz. 641, z 2010 r. Nr 96, poz. 620 oraz z 2011 r. Nr 112, poz. 654 i Nr 113, poz. 660. Pokaż całość var tree = [ { \"id\" : \"part_1\", \"title\" : \"Treść ustawy\", \"type\": \"part\", \"symbol\" : \"part_1\", \"children\" : [ {\"id\": \"arti_1\",\"symbol\": \"arti_1\",\"type\": \"arti\",\"name\": \"1\",\"title\": \"Art. 1.\",\"children\": [{\"id\": \"arti_1-pint_1\",\"symbol\": \"pint_1\",\"type\": \"pint\",\"name\": \"1\",\"title\": \"1)\"},{\"id\": \"arti_1-pint_2\",\"symbol\": \"pint_2\",\"type\": \"pint\",\"name\": \"2\",\"title\": \"2)\",\"children\": [{\"id\": \"arti_1-pint_2-lett_a\",\"symbol\": \"lett_a\",\"type\": \"lett\",\"name\": \"a\",\"title\": \"a)\"},{\"id\": \"arti_1-pint_2-lett_b\",\"symbol\": \"lett_b\",\"type\": \"lett\",\"name\": \"b\",\"title\": \"b)\"}]},{\"id\": \"arti_1-pint_3\",\"symbol\": \"pint_3\",\"type\": \"pint\",\"name\": \"3\",\"title\": \"3)\"},{\"id\": \"arti_1-pint_4\",\"symbol\": \"pint_4\",\"type\": \"pint\",\"name\": \"4\",\"title\": \"4)\"},{\"id\": \"arti_1-pint_5\",\"symbol\": \"pint_5\",\"type\": \"pint\",\"name\": \"5\",\"title\": \"5)\"}]},{\"id\": \"arti_2\",\"symbol\": \"arti_2\",\"type\": \"arti\",\"name\": \"2\",\"title\": \"Art. 2.\"},{\"id\": \"arti_3\",\"symbol\": \"arti_3\",\"type\": \"arti\",\"name\": \"3\",\"title\": \"Art. 3.\",\"children\": [{\"id\": \"arti_3-pass_1\",\"symbol\": \"pass_1\",\"type\": \"pass\",\"name\": \"1\",\"title\": \"1.\"},{\"id\": \"arti_3-pass_2\",\"symbol\": \"pass_2\",\"type\": \"pass\",\"name\": \"2\",\"title\": \"2.\"},{\"id\": \"arti_3-pass_3\",\"symbol\": \"pass_3\",\"type\": \"pass\",\"name\": \"3\",\"title\": \"3.\"}]},{\"id\": \"arti_4\",\"symbol\": \"arti_4\",\"type\": \"arti\",\"name\": \"4\",\"title\": \"Art. 4.\"},{\"id\": \"arti_5\",\"symbol\": \"arti_5\",\"type\": \"arti\",\"name\": \"5\",\"title\": \"Art. 5.\"} ] } ];"
    }
  ],
  "definitions": []
}