{
  "id": "pl-du-2016-580",
  "type": "statute",
  "title": "Ustawa z dnia 13 kwietnia 2016 r. zmieniająca ustawę o zmianie ustawy o systemie informacji w ochronie zdrowia oraz niektórych innych ustaw",
  "title_en": "",
  "short_name": "pl-du-2016-580",
  "status": "in_force",
  "issued_date": "2016-04-13",
  "in_force_date": "2016-04-27",
  "url": "https://api.sejm.gov.pl/eli/acts/DU/2016/580",
  "provisions": [
    {
      "provision_ref": "art1",
      "section": "1",
      "title": "Art. 1",
      "content": "W ustawie z dnia 9 października 2015 r. o zmianie ustawy o systemie informacji w ochronie zdrowia oraz niektórych innych ustaw ( Dz. U. poz. 1991 oraz z 2016 r. poz. 65 ) wprowadza się następujące zmiany: 1) w art. 19, art. 20 ust. 1 i 3, art. 21 ust. 1, 3 i 4, art. 22 ust. 1-4, art. 23 ust. 1 i art. 24-27 wyrazy „1 maja 2016 r.” zastępuje się wyrazami „1 maja 2017 r.” ; 2) w art. 20 po ust. 2 dodaje się ust. 2a w brzmieniu: „ 2a. Do lekarzy i lekarzy dentystów zakwalifikowanych do odbywania szkolenia specjalizacyjnego nie później niż w wyniku postępowania kwalifikacyjnego przeprowadzanego w okresie od dnia 1 marca 2017 r. do dnia 31 marca 2017 r., w zakresie odbywania przez nich szkolenia specjalizacyjnego, stosuje się dotychczasowe przepisy. ” ; 3) w art. 21: a) w ust. 1 i 3-5 wyrazy „31 lipca 2016 r.” zastępuje się wyrazami „31 lipca 2017 r.” , b) w ust. 2 wyrazy „31 maja 2016 r.” zastępuje się wyrazami „31 maja 2017 r.” ; 4) w art. 26: a) w ust. 1: - wyrazy „od dnia 1 października 2016 r. do dnia 30 listopada 2016 r.” zastępuje się wyrazami „od dnia 1 października 2017 r. do dnia 30 listopada 2017 r.” , - wyrazy „31 lipca 2016 r.” zastępuje się wyrazami „31 lipca 2017 r.” , b) w ust. 2: - wyrazy „od dnia 1 września 2016 r. do dnia 30 września 2016 r.” zastępuje się wyrazami „od dnia 1 września 2017 r. do dnia 30 września 2017 r.” , - wyrazy „30 czerwca 2016 r.” zastępuje się wyrazami „30 czerwca 2017 r.” ; 5) w art. 48: a) w ust. 1: - po pkt 4 dodaje się pkt 4a-4d w brzmieniu: „ 4a) art. 14e ust. 1 ustawy, o której mowa w art. 4, zachowują moc do dnia wejścia w życie przepisów wykonawczych wydanych na podstawie art. 14f ust. 1 ustawy, o której mowa w art. 4, w brzmieniu nadanym niniejszą ustawą, 4b) art. 16 ust. 10, art. 16g ust. 1 i art. 16x ust. 1 ustawy, o której mowa w art. 4, zachowują moc do dnia wejścia w życie przepisów wykonawczych wydanych na podstawie art. 16 ust. 10, art. 16g ust. 1 i art. 16x ust. 1 ustawy, o której mowa w art. 4, w brzmieniu nadanym niniejszą ustawą, 4c) art. 16r ust. 13 ustawy, o której mowa w art. 4, zachowują moc do dnia wejścia w życie przepisów wykonawczych wydanych na podstawie art. 16ra ust. 2 ustawy, o której mowa w art. 4, w brzmieniu nadanym niniejszą ustawą, 4d) art. 16t ust. 4 ustawy, o której mowa w art. 4, zachowują moc do dnia wejścia w życie przepisów wykonawczych wydanych na podstawie art. 16x ust. 1 ustawy, o której mowa w art. 4, w brzmieniu nadanym niniejszą ustawą, ” , - po pkt 11 dodaje się pkt 11a w brzmieniu: „ 11a) art. 56 ust. 3 ustawy, o której mowa w art. 7, zachowują moc do dnia wejścia w życie przepisów wykonawczych wydanych na podstawie art. 56 ust. 3 ustawy, o której mowa w art. 7, w brzmieniu nadanym niniejszą ustawą, ” , - w części wspólnej wyrazy „1 stycznia 2017 r.” zastępuje się wyrazami „1 stycznia 2018 r.” , b) uchyla się ust. 2 i 3, c) w ust. 4 wyrazy „1 stycznia 2017 r.” zastępuje się wyrazami „31 stycznia 2018 r.” , d) w ust. 5 wyrazy „1 stycznia 2017 r.” zastępuje się wyrazami „31 stycznia 2018 r.” , e) w ust. 6 wyrazy „1 maja 2016 r.” zastępuje się wyrazami „1 maja 2017 r.” ; 6) w art. 52: a) pkt 3 otrzymuje brzmienie: „ 3) art. 3 pkt 2, art. 5, art. 6 pkt 16 i art. 29-44, które wchodzą w życie z dniem 1 maja 2016 r.; ” , b) po pkt 5 dodaje się pkt 5a w brzmieniu: „ 5a) art. 4 pkt 2 lit. b i pkt 3-32, art. 9 pkt 1-4, 10 i 11, art. 15 pkt 8-17 i art. 19-28, które wchodzą w życie z dniem 1 maja 2017 r.; ” ."
    },
    {
      "provision_ref": "art2",
      "section": "2",
      "title": "Art. 2",
      "content": "Ustawa wchodzi w życie z dniem 30 kwietnia 2016 r. Pokaż całość var tree = [ { \"id\" : \"part_1\", \"title\" : \"Treść ustawy\", \"type\": \"part\", \"symbol\" : \"part_1\", \"children\" : [ {\"id\": \"arti_1\",\"symbol\": \"arti_1\",\"type\": \"arti\",\"name\": \"1\",\"title\": \"Art. 1.\",\"children\": [{\"id\": \"arti_1-pint_1\",\"symbol\": \"pint_1\",\"type\": \"pint\",\"name\": \"1\",\"title\": \"1)\"},{\"id\": \"arti_1-pint_2\",\"symbol\": \"pint_2\",\"type\": \"pint\",\"name\": \"2\",\"title\": \"2)\"},{\"id\": \"arti_1-pint_3\",\"symbol\": \"pint_3\",\"type\": \"pint\",\"name\": \"3\",\"title\": \"3)\",\"children\": [{\"id\": \"arti_1-pint_3-lett_a\",\"symbol\": \"lett_a\",\"type\": \"lett\",\"name\": \"a\",\"title\": \"a)\"},{\"id\": \"arti_1-pint_3-lett_b\",\"symbol\": \"lett_b\",\"type\": \"lett\",\"name\": \"b\",\"title\": \"b)\"}]},{\"id\": \"arti_1-pint_4\",\"symbol\": \"pint_4\",\"type\": \"pint\",\"name\": \"4\",\"title\": \"4)\",\"children\": [{\"id\": \"arti_1-pint_4-lett_a\",\"symbol\": \"lett_a\",\"type\": \"lett\",\"name\": \"a\",\"title\": \"a)\"},{\"id\": \"arti_1-pint_4-lett_b\",\"symbol\": \"lett_b\",\"type\": \"lett\",\"name\": \"b\",\"title\": \"b)\"}]},{\"id\": \"arti_1-pint_5\",\"symbol\": \"pint_5\",\"type\": \"pint\",\"name\": \"5\",\"title\": \"5)\",\"children\": [{\"id\": \"arti_1-pint_5-lett_a\",\"symbol\": \"lett_a\",\"type\": \"lett\",\"name\": \"a\",\"title\": \"a)\"},{\"id\": \"arti_1-pint_5-lett_b\",\"symbol\": \"lett_b\",\"type\": \"lett\",\"name\": \"b\",\"title\": \"b)\"},{\"id\": \"arti_1-pint_5-lett_c\",\"symbol\": \"lett_c\",\"type\": \"lett\",\"name\": \"c\",\"title\": \"c)\"},{\"id\": \"arti_1-pint_5-lett_d\",\"symbol\": \"lett_d\",\"type\": \"lett\",\"name\": \"d\",\"title\": \"d)\"},{\"id\": \"arti_1-pint_5-lett_e\",\"symbol\": \"lett_e\",\"type\": \"lett\",\"name\": \"e\",\"title\": \"e)\"}]},{\"id\": \"arti_1-pint_6\",\"symbol\": \"pint_6\",\"type\": \"pint\",\"name\": \"6\",\"title\": \"6)\",\"children\": [{\"id\": \"arti_1-pint_6-lett_a\",\"symbol\": \"lett_a\",\"type\": \"lett\",\"name\": \"a\",\"title\": \"a)\"},{\"id\": \"arti_1-pint_6-lett_b\",\"symbol\": \"lett_b\",\"type\": \"lett\",\"name\": \"b\",\"title\": \"b)\"}]}]},{\"id\": \"arti_2\",\"symbol\": \"arti_2\",\"type\": \"arti\",\"name\": \"2\",\"title\": \"Art. 2.\"} ] } ];"
    }
  ],
  "definitions": []
}