{
  "id": "pl-du-1932-68",
  "type": "statute",
  "title": "Ustawa z dnia 21 stycznia 1932 r. o dodatkowych kredytach na rok 1930/31.",
  "title_en": "",
  "short_name": "pl-du-1932-68",
  "status": "in_force",
  "issued_date": "1932-01-21",
  "in_force_date": "1932-02-19",
  "url": "https://api.sejm.gov.pl/eli/acts/DU/1932/68",
  "provisions": [
    {
      "provision_ref": "art1",
      "section": "1",
      "title": "Art. 1",
      "content": "Wydatki zwyczajne, ustalone w grupie A. Administracja budżetu, załączonego do ustawy skarbowej z dnia 29 marca 1930 r. na okres od 1 kwietnia 1930 r. do 31 marca 1931 r. (Dz. U. R. P. Nr 24, poz. 221), podwyższa się o nastąpujące kwoty: 1) w części 6. Ministerstwo Spraw Wojskowych: w dziale 10 § 1 „Uposażenie” o 207.827 zł 2) w części 8. Ministerstwo Skarbu: w dziale 3 § 1 „Uposażenie” o 59.112 „ w dziale 4 § 1 „Uposażenie” o 1.102.388 „ 3) w części 13. Ministerstwo Wyznań Religijnych i Oświecenia Publicznego: w dziale 2 § 14 „Wyznanie mojżeszowe” o 162 „ w dziale 3 § 1 „Uposażenie” o 218.169 „ w dziale 4 rozdział 2 § 1 „Uposażenie” o 7.317.492 „ w dziale 4 rozdział 3 § 1 „Uposażenie” o 426.950 „ w dziale 6 § 1 „Uposażenie” o 260.932 „ w dziale 7 rozdział 1 § 1 „Uposażenie” o 308.307 „ w dziale 8 rozdział 3 § 1 „Uposażenie” o 10.073 „ w dziale 8 rozdział 4 § 1 „Uposażenie” o 23.375 „ 4) w części 14. Ministerstwo Robót Publicznych: w dziale 1 § 1 „Uposażenie” o 33.411 „ 5) w części 18. Emerytury: w dziale 1 § 1 „Emerytury cywilne” o 39.082.126 „ w dziale 1 § 2 „Emerytury wojskowe” o 10.828.366 „ w dziale 1 § 4 „Pośmiertne” o 43.442 „ w dziale 1 § 5 „Zaopatrzenie osób szczególnie zasłużonych oraz zaopatrzenie nie oparte na innych tytułach prawnych” o 251.300 „ w dziale 1 § 6 „Koszty przesiedleń emerytów” o 209.884 „"
    },
    {
      "provision_ref": "art2",
      "section": "2",
      "title": "Art. 2",
      "content": "Ogólna suma wydatków, ustalonych w ustawie skarbowej z dnia 29 marca 1930 r. w kwocie 2.940.921.861 zł nie ulega zwiększeniu mimo postanowień art. 1 niniejszej ustawy, co zostaje osiągnięte przez zmniejszenie wydatków w innych paragrafach budżetu."
    },
    {
      "provision_ref": "art3",
      "section": "3",
      "title": "Art. 3",
      "content": "Upoważnia się Ministra Skarbu do przeniesienia w części 6 budżetu na r. 1930/31 kredytu w kwocie 600.000 zł z działu 3 § 11 wydatków zwyczajnych na dział 5 § 10 wydatków nadzwyczajnych."
    },
    {
      "provision_ref": "art4",
      "section": "4",
      "title": "Art. 4",
      "content": "Rozchody nadzwyczajne, ustalone w budżecie na rok 1930/31 dla przedsiębiorstwa „Państwowe Żupy Solne” (grupa B. część 10, dział 11 § 6 „wydatki nadzwyczajne”) zwiększa się o kwotę 175.000 zł. Na pokrycie powyższego zwiększenia służą wpływy zwyczajne wymienionego przedsiębiorstwa."
    },
    {
      "provision_ref": "art5",
      "section": "5",
      "title": "Art. 5",
      "content": "Skreśla się wpłatę przedsiębiorstwa „Państwowa Fabryka Związków Azotowych w Chorzowie”, przewidzianą w budżecie na rok 1930/31 (grupa B. część 10, dział 15) w sumie 2.500.000 zł."
    },
    {
      "provision_ref": "art6",
      "section": "6",
      "title": "Art. 6",
      "content": "Wykonanie niniejszej ustawy porucza się Ministrowi Skarbu."
    },
    {
      "provision_ref": "art7",
      "section": "7",
      "title": "Art. 7",
      "content": "Ustawa niniejsza wchodzi w życie z dniem ogłoszenia z mocą obowiązującą od 1 kwietnia 1930 r. Pokaż całość var tree = [ { \"id\" : \"part_1\", \"title\" : \"Treść ustawy\", \"type\": \"part\", \"symbol\" : \"part_1\", \"children\" : [ {\"id\": \"arti_1\",\"symbol\": \"arti_1\",\"type\": \"arti\",\"name\": \"1\",\"title\": \"Art. 1.\",\"children\": [{\"id\": \"arti_1-pint_1\",\"symbol\": \"pint_1\",\"type\": \"pint\",\"name\": \"1\",\"title\": \"1)\"},{\"id\": \"arti_1-pint_2\",\"symbol\": \"pint_2\",\"type\": \"pint\",\"name\": \"2\",\"title\": \"2)\"},{\"id\": \"arti_1-pint_3\",\"symbol\": \"pint_3\",\"type\": \"pint\",\"name\": \"3\",\"title\": \"3)\"},{\"id\": \"arti_1-pint_4\",\"symbol\": \"pint_4\",\"type\": \"pint\",\"name\": \"4\",\"title\": \"4)\"},{\"id\": \"arti_1-pint_5\",\"symbol\": \"pint_5\",\"type\": \"pint\",\"name\": \"5\",\"title\": \"5)\"}]},{\"id\": \"arti_2\",\"symbol\": \"arti_2\",\"type\": \"arti\",\"name\": \"2\",\"title\": \"Art. 2.\"},{\"id\": \"arti_3\",\"symbol\": \"arti_3\",\"type\": \"arti\",\"name\": \"3\",\"title\": \"Art. 3.\"},{\"id\": \"arti_4\",\"symbol\": \"arti_4\",\"type\": \"arti\",\"name\": \"4\",\"title\": \"Art. 4.\"},{\"id\": \"arti_5\",\"symbol\": \"arti_5\",\"type\": \"arti\",\"name\": \"5\",\"title\": \"Art. 5.\"},{\"id\": \"arti_6\",\"symbol\": \"arti_6\",\"type\": \"arti\",\"name\": \"6\",\"title\": \"Art. 6.\"},{\"id\": \"arti_7\",\"symbol\": \"arti_7\",\"type\": \"arti\",\"name\": \"7\",\"title\": \"Art. 7.\"} ] } ];"
    }
  ],
  "definitions": []
}