{
  "id": "pl-du-2016-2024",
  "type": "statute",
  "title": "Ustawa z dnia 1 grudnia 2016 r. o zmianie ustawy o podatku od towarów i usług oraz niektórych innych ustaw",
  "title_en": "",
  "short_name": "pl-du-2016-2024",
  "status": "in_force",
  "issued_date": "2016-12-01",
  "in_force_date": "2016-12-15",
  "url": "https://api.sejm.gov.pl/eli/acts/DU/2016/2024",
  "provisions": [
    {
      "provision_ref": "art1",
      "section": "1",
      "title": "Art. 1",
      "content": "W ustawie z dnia 11 marca 2004 r. o podatku od towarów i usług ( Dz. U. z 2016 r. poz. 710 , z późn. zm. 2) Zmiany tekstu jednolitego wymienionej ustawy zostały ogłoszone w Dz. U. z 2016 r. poz. 846, 960, 1052, 1206, 1228, 1579 i 1948. ) wprowadza się następujące zmiany: 1) w art. 17: a) w ust. 1 pkt 8 otrzymuje brzmienie: „ 8) nabywające usługi wymienione w załączniku nr 14 do ustawy, jeżeli łącznie spełnione są następujące warunki: a) usługodawcą jest podatnik, o którym mowa w art. 15, u którego sprzedaż nie jest zwolniona od podatku na podstawie art. 113 ust. 1 i 9, b) usługobiorcą jest podatnik, o którym mowa w art. 15, zarejestrowany jako podatnik VAT czynny. ” , b) w ust. 1c-1e wyrazy „poz. 28a-28c załącznika nr 11 do ustawy” zastępuje się wyrazami „poz. 28-28c załącznika nr 11 do ustawy” , c) po ust. 1g dodaje się ust. 1h w brzmieniu: „ 1h. W przypadku usług wymienionych w poz. 2-48 załącznika nr 14 do ustawy przepis ust. 1 pkt 8 stosuje się, jeżeli usługodawca świadczy te usługi jako podwykonawca. ” , d) w ust. 2a wyrazy „poz. 28a-28c załącznika nr 11 do ustawy” zastępuje się wyrazami „poz. 28-28c załącznika nr 11 do ustawy” ; 2) w art. 29a w ust. 15 pkt 3 otrzymuje brzmienie: „ 3) sprzedaży: energii elektrycznej, cieplnej lub chłodniczej, gazu przewodowego, usług dystrybucji energii elektrycznej, cieplnej lub chłodniczej, usług dystrybucji gazu przewodowego, usług telekomunikacyjnych oraz usług wymienionych w poz. 140-153, 174 i 175 załącznika nr 3 do ustawy; ” ; 3) w art. 43: a) uchyla się ust. 13 i 14, b) w ust. 15 wprowadzenie do wyliczenia otrzymuje brzmienie: „ Zwolnienia, o których mowa w ust. 1 pkt 7, 12 i 37-41, nie mają zastosowania do: ” ; 4) w art. 86: a) w ust. 10b: - w pkt 2 lit. b otrzymuje brzmienie: „ b) uwzględni kwotę podatku należnego z tytułu wewnątrzwspólnotowego nabycia towarów w deklaracji podatkowej, w której jest on obowiązany rozliczyć ten podatek, nie później niż w terminie 3 miesięcy od upływu miesiąca, w którym w odniesieniu do nabytych towarów powstał obowiązek podatkowy; ” , - pkt 3 otrzymuje brzmienie: „ 3) ust. 2 pkt 4 lit. a, b i d - powstaje zgodnie z ust. 10, pod warunkiem że podatnik uwzględni kwotę podatku należnego z tytułu tych transakcji w deklaracji podatkowej, w której jest on obowiązany rozliczyć ten podatek, nie później niż w terminie 3 miesięcy od upływu miesiąca, w którym w odniesieniu do nabytych towarów lub usług powstał obowiązek podatkowy. ” , b) po ust. 10h dodaje się ust. 10i w brzmieniu: „ 10i. W przypadku uwzględnienia przez podatnika kwoty podatku należnego w deklaracji podatkowej, w której jest on obowiązany rozliczyć ten podatek, w terminie późniejszym niż określony w ust. 10b pkt 2 lit. b i pkt 3, podatnik może odpowiednio zwiększyć kwotę podatku naliczonego w rozliczeniu za okres rozliczeniowy, w odniesieniu do którego nie upłynął jeszcze termin do złożenia deklaracji podatkowej. ” ; 5) w art. 87: a) w ust. 2 zdanie pierwsze otrzymuje brzmienie: „ Zwrot różnicy podatku, z zastrzeżeniem ust. 6, następuje w terminie 60 dni od dnia złożenia rozliczenia przez podatnika na rachunek bankowy podatnika w banku mającym siedzibę na terytorium kraju albo na rachunek podatnika w spółdzielczej kasie oszczędnościowo-kredytowej, której jest członkiem, wskazany w zgłoszeniu identyfikacyjnym, o którym mowa w odrębnych przepisach, lub na wskazany przez podatnika rachunek banku mającego siedzibę na terytorium kraju lub na rachunek spółdzielczej kasy oszczędnościowo-kredytowej, jako zabezpieczenie udzielanego przez ten bank lub przez tę kasę kredytu, na podstawie złożonego przez podatnika do naczelnika urzędu skarbowego, w terminie do złożenia deklaracji podatkowej, pisemnego, nieodwołalnego upoważnienia organu podatkowego, potwierdzonego przez bank lub spółdzielczą kasę oszczędnościowo-kredytową udzielających kredytu, do przekazania tego zwrotu. ” , b) po ust. 2a dodaje się ust. 2b i 2c w brzmieniu: „ 2b. Weryfikacja zasadności zwrotu różnicy podatku może obejmować sprawdzenie rozliczenia podatnika, rozliczeń innych podmiotów biorących udział w obrocie towarami lub usługami, będącymi przedmiotem rozliczenia podatnika, oraz sprawdzenie zgodności tych rozliczeń z faktycznym przebiegiem transakcji. 2c. Naczelnik urzędu skarbowego przedłuża podatnikowi termin zwrotu różnicy podatku, o którym mowa w ust. 2, 5a i 6, na podstawie żądania zgłoszonego przez Komendanta Głównego Policji, Szefa Centralnego Biura Antykorupcyjnego, Szefa Agencji Bezpieczeństwa Wewnętrznego lub Prokuratora Generalnego w związku z prowadzonym postępowaniem na okres wskazany w żądaniu, nie dłuższy niż 3 miesiące. Żądanie zawiera uzasadnienie. Przepis ust. 2 zdanie trzecie stosuje się odpowiednio. ” , c) w ust. 5 zdanie drugie otrzymuje brzmienie: „ Przepisy ust. 2 zdanie drugie i trzecie, ust. 2a-2c oraz ust. 4a-4f stosuje się odpowiednio. ” , d) w ust. 5a zdanie trzecie otrzymuje brzmienie: „ Przepisy ust. 2 zdanie drugie i trzecie, ust. 2a-2c oraz ust. 4a-4f stosuje się odpowiednio. ” , e) ust. 6 otrzymuje brzmienie: „ 6. Na wniosek podatnika, złożony wraz z deklaracją podatkową, urząd skarbowy jest obowiązany dokonać zwrotu różnicy podatku, o której mowa w ust. 2, w terminie 25 dni, licząc od dnia złożenia rozliczenia, w przypadku gdy łącznie spełnione są następujące warunki: 1) kwoty podatku naliczonego, wykazane w deklaracji podatkowej, z wyłączeniem kwoty podatku naliczonego lub różnicy podatku, o której mowa w ust. 1, nierozliczonej w poprzednich okresach rozliczeniowych i wykazanej w deklaracji, wynikają z: a) faktur dokumentujących kwoty należności, które zostały w całości zapłacone za pośrednictwem rachunku bankowego podatnika w banku mającym siedzibę na terytorium kraju albo rachunku podatnika w spółdzielczej kasie oszczędnościowo-kredytowej, której jest członkiem, wskazanego w zgłoszeniu identyfikacyjnym, o którym mowa w odrębnych przepisach, b) faktur, innych niż wymienione w lit. a, dokumentujących należności, jeżeli łączna kwota tych należności nie przekracza 15 000 zł, c) dokumentów celnych, deklaracji importowej oraz decyzji, o których mowa w art. 33 ust. 2 i 3 oraz art. 34, i zostały przez podatnika zapłacone, d) importu towarów rozliczanego zgodnie z art. 33a, wewnątrzwspólnotowego nabycia towarów, świadczenia usług, dla którego podatnikiem jest ich usługobiorca, lub dostawy towarów, dla której podatnikiem jest ich nabywca, jeżeli w deklaracji podatkowej została wykazana kwota podatku należnego od tych transakcji, 2) kwota podatku naliczonego lub różnicy podatku, o której mowa w ust. 1, nierozliczona w poprzednich okresach rozliczeniowych i wykazana w deklaracji nie przekracza 3000 zł, 3) podatnik złoży w urzędzie skarbowym dokumenty potwierdzające zapłatę podatku za pośrednictwem rachunku bankowego podatnika albo rachunku podatnika w spółdzielczej kasie oszczędnościowo-kredytowej, o których mowa w ust. 2, 4) podatnik przez kolejne 12 miesięcy poprzedzających bezpośrednio okres, w rozliczeniu za który występuje z wnioskiem o zwrot w terminie 25 dni: a) był zarejestrowany jako podatnik VAT czynny, b) składał za każdy okres rozliczeniowy deklaracje, o których mowa w art. 99 ust. 1-3 - przy czym przepisy ust. 2 zdanie drugie i trzecie, ust. 2a-2c oraz ust. 4a-4f stosuje się odpowiednio. ” , f) ust. 10 otrzymuje brzmienie: „ 10. Do zwrotu różnicy podatku podatnikowi, o którym mowa w art. 16, stosuje się odpowiednio przepisy ust. 2-2c, 6 i 7. ” ; 6) w art. 89b uchyla się ust. 6; 7) w art. 90 po ust. 10 dodaje się ust. 10a i 10b w brzmieniu: „ 10a. W przypadku jednostki samorządu terytorialnego proporcję, o której mowa w ust. 2, ustala się odrębnie dla każdej z jednostek organizacyjnych jednostki samorządu terytorialnego. Przepisy ust. 3-6 i 8-10 stosuje się odpowiednio. 10b. Przez jednostki organizacyjne jednostki samorządu terytorialnego, o których mowa w ust. 10a, rozumie się: 1) utworzone przez jednostkę samorządu terytorialnego samorządową jednostkę budżetową lub samorządowy zakład budżetowy; 2) urząd gminy, starostwo powiatowe, urząd marszałkowski. ” ; 8) w art. 90a w ust. 1 zdanie trzecie otrzymuje brzmienie: „ Jeżeli podatnik wykorzystuje tę nieruchomość w działalności gospodarczej również do czynności zwolnionych od podatku bez prawa do odliczeń, korekta powinna uwzględniać proporcję określoną w art. 90 ust. 3-10a, zastosowaną przy odliczeniu. ” ; 9) w art. 91 ust. 1 otrzymuje brzmienie: „ 1. Po zakończeniu roku, w którym podatnikowi przysługiwało prawo do obniżenia kwoty podatku należnego o kwotę podatku naliczonego, o którym mowa w art. 86 ust. 1, jest on obowiązany dokonać korekty kwoty podatku odliczonego zgodnie z art. 90 ust. 2-10a, z uwzględnieniem proporcji obliczonej w sposób określony w art. 90 ust. 2-6, 10 lub 10a lub przepisach wydanych na podstawie art. 90 ust. 11 i 12, dla zakończonego roku podatkowego. ” ; 10) w art. 96: a) ust. 4 otrzymuje brzmienie: „ 4. Naczelnik urzędu skarbowego po weryfikacji danych podanych w zgłoszeniu rejestracyjnym rejestruje podatnika jako „podatnika VAT czynnego”, a w przypadku podatników, o których mowa w ust. 3 - jako „podatnika VAT zwolnionego”, i na wniosek podatnika potwierdza to zarejestrowanie. ” , b) po ust. 4 dodaje się ust. 4a-4c w brzmieniu: „ 4a. Naczelnik urzędu skarbowego nie dokonuje rejestracji podmiotu jako podatnika VAT bez konieczności zawiadamiania podmiotu, jeżeli: 1) dane podane w zgłoszeniu rejestracyjnym są niezgodne z prawdą lub 2) podmiot ten nie istnieje, lub 3) mimo podjętych udokumentowanych prób nie ma możliwości skontaktowania się z tym podmiotem albo jego pełnomocnikiem, lub 4) podmiot albo jego pełnomocnik nie stawia się na wezwania naczelnika urzędu skarbowego. 4b. W przypadku zarejestrowania podatnika, którego zgłoszenie rejestracyjne zostało złożone przez pełnomocnika, pełnomocnik odpowiada solidarnie wraz z zarejestrowanym podatnikiem do kwoty 500 000 zł za zaległości podatkowe podatnika powstałe z tytułu czynności wykonanych w ciągu 6 miesięcy od dnia zarejestrowania podatnika jako podatnika VAT czynnego. 4c. Przepisu ust. 4b nie stosuje się, jeżeli powstanie zaległości podatkowych nie wiązało się z uczestnictwem podatnika w nierzetelnym rozliczaniu podatku w celu odniesienia korzyści majątkowej. ” , c) ust. 9 otrzymuje brzmienie: „ 9. Naczelnik urzędu skarbowego wykreśla z urzędu podatnika z rejestru jako podatnika VAT bez konieczności zawiadamiania o tym podatnika, jeżeli: 1) podatnik nie istnieje lub 2) mimo podjętych udokumentowanych prób nie ma możliwości skontaktowania się z podatnikiem albo jego pełnomocnikiem, lub 3) dane podane w zgłoszeniu rejestracyjnym okażą się niezgodne z prawdą, lub 4) podatnik albo jego pełnomocnik nie stawia się na wezwania organu podatkowego lub organu kontroli skarbowej. ” , d) po ust. 9 dodaje się ust. 9a-9i w brzmieniu: „ 9a. Wykreśleniu z urzędu z rejestru jako podatnik VAT podlega także podatnik, który: 1) zawiesił wykonywanie działalności gospodarczej na podstawie przepisów o swobodzie działalności gospodarczej na okres co najmniej 6 kolejnych miesięcy lub 2) będąc obowiązanym do złożenia deklaracji, o której mowa w art. 99 ust. 1, 2 lub 3, nie złożył takich deklaracji za 6 kolejnych miesięcy lub 2 kolejne kwartały, lub 3) składał przez 6 kolejnych miesięcy lub 2 kolejne kwartały deklaracje, o których mowa w art. 99 ust. 1, 2 lub 3, w których nie wykazał sprzedaży lub nabycia towarów lub usług z kwotami podatku do odliczenia, lub 4) wystawiał faktury lub faktury korygujące, dokumentujące czynności, które nie zostały dokonane, lub 5) prowadząc działalność gospodarczą wiedział lub miał uzasadnione podstawy do tego, aby przypuszczać, że dostawcy lub nabywcy biorący udział pośrednio lub bezpośrednio w dostawie tego samego towaru lub usługi uczestniczą w nierzetelnym rozliczaniu podatku w celu odniesienia korzyści majątkowej - z zastrzeżeniem ust. 9b-9f. 9b. Jeżeli podatnik, o którym mowa w ust. 9a pkt 1, w okresie zawieszenia działalności gospodarczej będzie wykonywał czynności, o których mowa w art. 5 ust. 1, jest "
    },
    {
      "provision_ref": "art2",
      "section": "2",
      "title": "Art. 2",
      "content": "W ustawie z dnia 13 października 1995 r. o zasadach ewidencji i identyfikacji podatników i płatników ( Dz. U. z 2016 r. poz. 476 i 1948 ) w art. 15 w ust. 1b zdanie pierwsze otrzymuje brzmienie: „ Tajemnicą skarbową nie są objęte dane z Krajowego Rejestru Sądowego, NIP, numer identyfikacyjny REGON, numer rachunku, o którym mowa w art. 105b ust. 1 pkt 4 ustawy z dnia 11 marca 2004 r. o podatku od towarów i usług , oraz dane przekazane na podstawie art. 14 ust. 3a i 3b przez CRP KEP za pośrednictwem systemu teleinformatycznego do krajowego rejestru urzędowego podmiotów gospodarki narodowej i do Centralnego Rejestru Płatników Składek. ” ."
    },
    {
      "provision_ref": "art3",
      "section": "3",
      "title": "Art. 3",
      "content": "W ustawie z dnia 29 sierpnia 1997 r. - Ordynacja podatkowa ( Dz. U. z 2015 r. poz. 613 , z późn. zm. 3) Zmiany tekstu jednolitego wymienionej ustawy zostały ogłoszone w Dz. U. z 2015 r. poz. 699, 978, 1197, 1269, 1311, 1649, 1923, 1932 i 2184 oraz z 2016 r. poz. 195, 615, 846, 1228, 1579, 1933 i 1948. ) wprowadza się następujące zmiany: 1) po art. 56b dodaje się art. 56ba w brzmieniu: „ Art. 56ba. Przepisu art. 56b nie stosuje się do zaległości w podatku od towarów i usług, w przypadku gdy ustala się dodatkowe zobowiązanie podatkowe, o którym mowa w art. 112b lub art. 112c ustawy o podatku od towarów i usług . ” ; 2) w art. 73 w § 2 uchyla się pkt 4; 3) w art. 77 w § 1 uchyla się pkt 7; 4) w art. 78 w § 3 uchyla się pkt 5; 5) po art. 117b dodaje się art. 117c w brzmieniu: „ Art. 117c. Pełnomocnik, o którym mowa w art. 96 ust. 4b ustawy o podatku od towarów i usług , odpowiada całym swoim majątkiem solidarnie z podatnikiem za zaległości podatkowe podatnika powstałe z tytułu czynności wykonanych w ciągu 6 miesięcy od dnia zarejestrowania podatnika jako podatnika VAT czynnego, na zasadach określonych w przepisach o podatku od towarów i usług. Przepisu art. 107 § 2 nie stosuje się. ” ; 6) w art. 118 § 1 otrzymuje brzmienie: „ § 1. Nie można wydać decyzji o odpowiedzialności podatkowej osoby trzeciej, jeżeli od końca roku kalendarzowego, w którym powstała zaległość podatkowa, upłynęło 5 lat, a w przypadku, o którym mowa: 1) w art. 117b § 1 - jeżeli od końca roku kalendarzowego, w którym miała miejsce dostawa towarów, upłynęły 3 lata; 2) w art. 117c - jeżeli od końca roku kalendarzowego, w którym upływa 6-miesięczny okres od dnia zarejestrowania podatnika jako podatnika VAT czynnego, upłynęły 3 lata. ” ; 7) w art. 133 § 1 otrzymuje brzmienie: „ § 1. Stroną w postępowaniu podatkowym jest podatnik, płatnik, inkasent lub ich następca prawny, a także osoba trzecia, o której mowa w art. 110-117c, która z uwagi na swój interes prawny żąda czynności organu podatkowego, do której czynność organu podatkowego się odnosi lub której interesu prawnego działanie organu podatkowego dotyczy. ” ; 8) w art. 274c po § 1b dodaje się § 1c w brzmieniu: „ § 1c. Przepisy § 1-1b stosuje się także do podmiotów prowadzących działalność gospodarczą uczestniczących w dostawie tego samego towaru lub świadczeniu tej samej usługi będących zarówno dostawcami, jak i nabywcami biorącymi udział pośrednio lub bezpośrednio w dostawie towaru lub świadczeniu usługi. W takim przypadku żądanie, o którym mowa w § 1, może dotyczyć wyłącznie dokumentów związanych z tą dostawą towaru lub tym świadczeniem usługi. ” ."
    },
    {
      "provision_ref": "art4",
      "section": "4",
      "title": "Art. 4",
      "content": "W ustawie z dnia 10 września 1999 r. - Kodeks karny skarbowy ( Dz. U. z 2013 r. poz. 186 , z późn. zm. 4) Zmiany tekstu jednolitego wymienionej ustawy zostały ogłoszone w Dz. U. z 2013 r. poz. 1036, 1149, 1247 i 1304, z 2014 r. poz. 312, 1215 i 1328, z 2015 r. poz. 396, 1269, 1479, 1649, 1712, 1855 i 1932 oraz z 2016 r. poz. 178, 437, 1052, 1228 i 1948. ) wprowadza się następujące zmiany: 1) w art. 9 § 3 otrzymuje brzmienie: „ § 3. Za przestępstwa skarbowe lub wykroczenia skarbowe odpowiada, jak sprawca, także ten, kto na podstawie przepisu prawa, decyzji właściwego organu, umowy lub faktycznego wykonywania zajmuje się sprawami gospodarczymi, w szczególności finansowymi, osoby fizycznej, osoby prawnej albo jednostki organizacyjnej niemającej osobowości prawnej. ” ; 2) w art. 37: a) w § 1 po pkt 1 dodaje się pkt 1a w brzmieniu: „ 1a) popełnia przestępstwo skarbowe określone w art. 62 § 2, a kwota podatku wynikająca z faktury albo suma kwot podatku wynikających z faktur jest dużej wartości; ” , b) po § 2 dodaje się § 2a w brzmieniu: „ § 2a. Przepisu § 1 pkt 1a nie stosuje się, jeżeli wymagalna należność została w całości uiszczona przed zamknięciem przewodu sądowego w pierwszej instancji. ” ; 3) w art. 38: a) w § 1 pkt 3 otrzymuje brzmienie: „ 3) przewidzianą za przypisane przestępstwo skarbowe w wysokości powyżej dolnej granicy ustawowego zagrożenia, nie niższej niż 1 miesiąc do górnej granicy ustawowego zagrożenia zwiększonego o połowę, co nie wyłącza wymierzenia z takim samym obostrzeniem także kary grzywny grożącej za to przestępstwo obok kary pozbawienia wolności. ” , b) w § 2: - wprowadzenie do wyliczenia otrzymuje brzmienie: „ Stosując nadzwyczajne obostrzenie kary, sąd wymierza karę pozbawienia wolności w wysokości powyżej dolnej granicy ustawowego zagrożenia, nie niższej niż 3 miesiące do górnej granicy ustawowego zagrożenia zwiększonego podwójnie, co nie wyłącza wymierzenia w wysokości do górnej granicy ustawowego zagrożenia zwiększonego o połowę także kary grzywny grożącej za to przestępstwo, jeżeli sprawca popełnia ten czyn zabroniony określony w: ” , - dodaje się pkt 3 w brzmieniu: „ 3) art. 62 § 2, a kwota podatku wynikająca z faktury albo suma kwot podatku wynikających z faktur stanowiących przedmiot czynu zabronionego jest wielkiej wartości. ” ; 4) w art. 50 uchyla się § 2; 5) w art. 56 § 4 otrzymuje brzmienie: „ § 4. Karze określonej w § 3 podlega także ten podatnik, który mimo ujawnienia przedmiotu lub podstawy opodatkowania nie składa w terminie organowi podatkowemu lub płatnikowi deklaracji lub oświadczenia lub wbrew obowiązkowi nie składa ich za pomocą środków komunikacji elektronicznej. ” ; 6) w art. 62: a) § 1 i 2 otrzymują brzmienie: „ § 1. Kto wbrew obowiązkowi nie wystawia faktury lub rachunku, wystawia je w sposób wadliwy albo odmawia ich wydania, podlega karze grzywny do 180 stawek dziennych. § 2. Kto fakturę lub rachunek wystawia w sposób nierzetelny albo takim dokumentem się posługuje, podlega karze grzywny do 720 stawek dziennych albo karze pozbawienia wolności na czas nie krótszy od roku, albo obu tym karom łącznie. ” , b) po § 2 dodaje się § 2a w brzmieniu: „ § 2a. Kto fakturę lub rachunek wystawia w sposób nierzetelny albo takim dokumentem się posługuje, a kwota podatku wynikająca z faktury albo suma kwot podatku wynikających z faktur jest małej wartości, podlega karze grzywny do 720 stawek dziennych albo karze pozbawienia wolności, albo obu tym karom łącznie. ” ; 7) w art. 80a § 2 otrzymuje brzmienie: „ § 2. Kto, wbrew obowiązkowi, nie składa w terminie właściwemu organowi informacji podsumowującej lub wbrew obowiązkowi nie składa jej za pomocą środków komunikacji elektronicznej, podlega karze grzywny za wykroczenie skarbowe. ” ."
    },
    {
      "provision_ref": "art5",
      "section": "5",
      "title": "Art. 5",
      "content": "Przepisy art. 17 ust. 1 pkt 8 ustawy zmienianej w art. 1, w brzmieniu nadanym niniejszą ustawą, stosuje się do usług wymienionych w poz. 2-48 załącznika nr 14 do ustawy zmienianej w art. 1, w brzmieniu nadanym niniejszą ustawą, które zostały wykonane od dnia 1 stycznia 2017 r. W celu ustalenia momentu wykonania usług stosuje się przepisy art. 19a ust. 2 i 3 ustawy zmienianej w art. 1."
    },
    {
      "provision_ref": "art6",
      "section": "6",
      "title": "Art. 6",
      "content": "W przypadku uiszczenia przed dniem 1 stycznia 2017 r. całości lub części zapłaty na poczet wykonanych od tego dnia usług wymienionych w poz. 1 załącznika nr 14 do ustawy zmienianej w art. 1, w brzmieniu nadanym niniejszą ustawą, dla których podatnikiem od dnia 1 stycznia 2017 r. przestał być nabywca zgodnie z art. 17 ust. 1 pkt 8 ustawy zmienianej w art. 1, w brzmieniu nadanym niniejszą ustawą, do usług tych stosuje się przepis art. 17 ust. 1 pkt 8 ustawy zmienianej w art. 1, w brzmieniu dotychczasowym."
    },
    {
      "provision_ref": "art7",
      "section": "7",
      "title": "Art. 7",
      "content": "W przypadku zawarcia przed dniem 1 stycznia 2017 r. umowy lub umów, w ramach których występują dostawy towarów wymienionych w poz. 28 załącznika nr 11 do ustawy zmienianej w art. 1, w brzmieniu nadanym niniejszą ustawą, przepisy art. 17 ust. 1c-1e ustawy zmienianej w art. 1, w brzmieniu nadanym niniejszą ustawą, stosuje się odpowiednio do tych dostaw dokonanych od dnia 1 stycznia 2017 r., jeżeli łączna wartość tych dostaw, bez kwoty podatku, przekracza od dnia 1 stycznia 2017 r. kwotę 20 000 zł."
    },
    {
      "provision_ref": "art8",
      "section": "8",
      "title": "Art. 8",
      "content": "W przypadku uiszczenia przed dniem 1 stycznia 2017 r. całości lub części zapłaty na poczet dokonanych od tego dnia dostaw towarów lub świadczenia usług, dla których podatnikiem od dnia 1 stycznia 2017 r. stał się nabywca zgodnie z art. 17 ust. 1 pkt 7 lub 8 ustawy zmienianej w art. 1, w brzmieniu nadanym niniejszą ustawą, korekty rozliczenia tej zapłaty dokonuje się w rozliczeniu za okres, w którym dokonano dostawy tych towarów lub wykonano tę usługę."
    },
    {
      "provision_ref": "art9",
      "section": "9",
      "title": "Art. 9",
      "content": "Do rozliczeń za okresy rozliczeniowe poprzedzające pierwszy okres rozliczeniowy 2017 r. stosuje się przepisy art. 86 ustawy zmienianej w art. 1, w brzmieniu dotychczasowym."
    },
    {
      "provision_ref": "art10",
      "section": "10",
      "title": "Art. 10",
      "content": "Przepis art. 87 ust. 2b ustawy zmienianej w art. 1, w brzmieniu nadanym niniejszą ustawą, oraz art. 274c § 1c ustawy zmienianej w art. 3, w brzmieniu nadanym niniejszą ustawą, stosuje się również do okresów rozliczeniowych przypadających przed dniem 1 stycznia 2017 r."
    },
    {
      "provision_ref": "art11",
      "section": "11",
      "title": "Art. 11",
      "content": "Przepisów art. 87 ust. 6, art. 112b i art. 112c ustawy zmienianej w art. 1, w brzmieniu nadanym niniejszą ustawą, nie stosuje się do okresów rozliczeniowych przypadających przed dniem 1 stycznia 2017 r."
    },
    {
      "provision_ref": "art12",
      "section": "12",
      "title": "Art. 12",
      "content": "Do okresów rozliczeniowych przypadających przed dniem 1 stycznia 2017 r. przepis art. 89b ust. 6 ustawy zmienianej w art. 1 stosuje się w brzmieniu dotychczasowym."
    },
    {
      "provision_ref": "art13",
      "section": "13",
      "title": "Art. 13",
      "content": "1. Przepisy art. 96 ustawy zmienianej w art. 1, w brzmieniu nadanym niniejszą ustawą, stosuje się do zgłoszeń rejestracyjnych złożonych od dnia 1 stycznia 2017 r., z wyjątkiem przepisów art. 96 ust. 4, 4a, 9 i 9a ustawy zmienianej w art. 1. 2. Przepisy art. 97 ust. 15 i 15a ustawy zmienianej w art. 1, w brzmieniu nadanym niniejszą ustawą, stosuje się z uwzględnieniem okresów przypadających przed dniem 1 stycznia 2017 r."
    },
    {
      "provision_ref": "art14",
      "section": "14",
      "title": "Art. 14",
      "content": "Przepisy art. 99-101a ustawy zmienianej w art. 1, w brzmieniu nadanym niniejszą ustawą, stosuje się począwszy od rozliczenia za pierwszy okres rozliczeniowy 2017 r."
    },
    {
      "provision_ref": "art15",
      "section": "15",
      "title": "Art. 15",
      "content": "Przepis art. 99 ust. 3a pkt 1 ustawy zmienianej w art. 1, w brzmieniu nadanym niniejszą ustawą, stosuje się do podatników, którzy zostali zarejestrowani jako podatnicy VAT czynni po dniu 30 września 2016 r. za okresy miesięczne przypadające po dniu 31 grudnia 2016 r."
    },
    {
      "provision_ref": "art16",
      "section": "16",
      "title": "Art. 16",
      "content": "W odniesieniu do okresów rozliczeniowych przypadających od dnia 1 stycznia do dnia 31 grudnia 2017 r. nie stosuje się przepisu art. 99 ust. 11b ustawy zmienianej w art. 1, w brzmieniu nadanym niniejszą ustawą, w stosunku do podatników, którzy nie są: 1) obowiązani do zarejestrowania się jako podatnik VAT UE; 2) dostawcami towarów lub świadczącymi usługi, dla których podatnikiem jest nabywca zgodnie z art. 17 ust. 1 pkt 7 i 8 ustawy zmienianej w art. 1, w brzmieniu nadanym niniejszą ustawą, lub nabywcami tych towarów lub usług; 3) obowiązani, zgodnie z art. 45ba ustawy z dnia 26 lipca 1991 r. o podatku dochodowym od osób fizycznych ( Dz. U. z 2012 r. poz. 361 , z późn. zm. 5) Zmiany tekstu jednolitego wymienionej ustawy zostały ogłoszone w Dz. U. z 2012 r. poz. 362, 596, 769, 1278, 1342, 1448, 1529 i 1540, z 2013 r. poz. 888, 1027, 1036, 1287, 1304, 1387 i 1717, z 2014 r. poz. 223, 312, 567, 598, 773, 915, 1052, 1215, 1328, 1563, 1644, 1662 i 1863, z 2015 r. poz. 73, 211, 251, 478, 693, 699, 860, 933, 978, 1197, 1217, 1259, 1296, 1321, 1322, 1333, 1569, 1595, 1607, 1688, 1767, 1784, 1844, 1893, 1925, 1932, 1992 i 2299 oraz z 2016 r. poz. 188, 195, 615, 780, 823, 929, 1010, 1206, 1550, 1860, 1926, 1933, 1948 i 1961. ) lub art. 27 ust. 1c ustawy z dnia 15 lutego 1992 r. o podatku dochodowym od osób prawnych ( Dz. U. z 2016 r. poz. 1888 , 1926 , 1933 i 1948 ) , do składania deklaracji, zeznań, informacji oraz rocznego obliczenia podatku za pomocą środków komunikacji elektronicznej."
    },
    {
      "provision_ref": "art17",
      "section": "17",
      "title": "Art. 17",
      "content": "1. Podmioty, które przed dniem 1 stycznia 2017 r. zostały wpisane do wykazu, o którym mowa w art. 105c ust. 1 ustawy zmienianej w art. 1, są obowiązane w terminie do dnia 31 stycznia 2017 r., do spełnienia wymogu, o którym mowa w art. 105b ust. 1 pkt 4 ustawy zmienianej w art. 1, w brzmieniu nadanym niniejszą ustawą, pod rygorem usunięcia w dniu 1 lutego 2017 r. przez właściwego naczelnika urzędu skarbowego z wykazu, o którym mowa w art. 105c ust. 1 ustawy zmienianej w art. 1. 2. Podmioty, które przed dniem 1 stycznia 2017 r. zostały wpisane do wykazu, o którym mowa w art. 105c ust. 1 ustawy zmienianej w art. 1, które w dniu 1 stycznia 2017 r. nie spełniają wymogów, o których mowa w art. 105b ust. 1 pkt 2 i 3 ustawy zmienianej w art. 1, w brzmieniu nadanym niniejszą ustawą, właściwy naczelnik urzędu skarbowego usuwa z wykazu, o którym mowa w art. 105c ust. 1 ustawy zmienianej w art. 1. 3. W przypadkach, o których mowa w ust. 1 i 2, wydaje się postanowienie, na które nie przysługuje zażalenie."
    },
    {
      "provision_ref": "art18",
      "section": "18",
      "title": "Art. 18",
      "content": "1. Podatnicy, u których łączna wartość sprzedaży w 2016 r. była wyższa niż 150 000 zł i nie przekroczyła 200 000 zł, mogą skorzystać ze zwolnienia, o którym mowa w art. 113 ust. 1 ustawy zmienianej w art. 1, w brzmieniu nadanym niniejszą ustawą. 2. Podatnicy, którzy rozpoczęli w 2016 r. wykonywanie czynności określonych w art. 5 ustawy zmienianej w art. 1, u których łączna wartość sprzedaży, w proporcji do okresu prowadzonej działalności gospodarczej, przekroczyła 150 000 zł i nie przekroczyła 200 000 zł, mogą skorzystać ze zwolnienia, o którym mowa w art. 113 ust. 1 ustawy zmienianej w art. 1, w brzmieniu nadanym niniejszą ustawą."
    },
    {
      "provision_ref": "art19",
      "section": "19",
      "title": "Art. 19",
      "content": "Przepisy art. 73, art. 77 i art. 78 ustawy zmienianej w art. 3, w brzmieniu dotychczasowym, stosuje się do rozliczeń poprzedzających pierwszy okres rozliczeniowy 2017 r."
    },
    {
      "provision_ref": "art20",
      "section": "20",
      "title": "Art. 20",
      "content": "Przepisy art. 105a ust. 3 pkt 3 lit. c i pkt 4 lit. d ustawy zmienianej w art. 1, w brzmieniu nadanym niniejszą ustawą, stosuje się od dnia 1 lutego 2017 r."
    },
    {
      "provision_ref": "art21",
      "section": "21",
      "title": "Art. 21",
      "content": "Ustawa wchodzi w życie z dniem 1 stycznia 2017 r., z wyjątkiem: 1) art. 1 pkt 3, który wchodzi w życie z dniem 1 lipca 2017 r.; 2) art. 1 pkt 7-9, które wchodzą w życie z dniem 1 stycznia 2018 r. 1) Niniejszą ustawą zmienia się ustawy: ustawę z dnia 13 października 1995 r. o zasadach ewidencji i identyfikacji podatników i płatników, ustawę z dnia 29 sierpnia 1997 r. - Ordynacja podatkowa oraz ustawę z dnia 10 września 1999 r. - Kodeks karny skarbowy. 2) Zmiany tekstu jednolitego wymienionej ustawy zostały ogłoszone w Dz. U. z 2016 r. poz. 846, 960, 1052, 1206, 1228, 1579 i 1948. 3) Zmiany tekstu jednolitego wymienionej ustawy zostały ogłoszone w Dz. U. z 2015 r. poz. 699, 978, 1197, 1269, 1311, 1649, 1923, 1932 i 2184 oraz z 2016 r. poz. 195, 615, 846, 1228, 1579, 1933 i 1948. 4) Zmiany tekstu jednolitego wymienionej ustawy zostały ogłoszone w Dz. U. z 2013 r. poz. 1036, 1149, 1247 i 1304, z 2014 r. poz. 312, 1215 i 1328, z 2015 r. poz. 396, 1269, 1479, 1649, 1712, 1855 i 1932 oraz z 2016 r. poz. 178, 437, 1052, 1228 i 1948. 5) Zmiany tekstu jednolitego wymienionej ustawy zostały ogłoszone w Dz. U. z 2012 r. poz. 362, 596, 769, 1278, 1342, 1448, 1529 i 1540, z 2013 r. poz. 888, 1027, 1036, 1287, 1304, 1387 i 1717, z 2014 r. poz. 223, 312, 567, 598, 773, 915, 1052, 1215, 1328, 1563, 1644, 1662 i 1863, z 2015 r. poz. 73, 211, 251, 478, 693, 699, 860, 933, 978, 1197, 1217, 1259, 1296, 1321, 1322, 1333, 1569, 1595, 1607, 1688, 1767, 1784, 1844, 1893, 1925, 1932, 1992 i 2299 oraz z 2016 r. poz. 188, 195, 615, 780, 823, 929, 1010, 1206, 1550, 1860, 1926, 1933, 1948 i 1961. Załącznik - Tekst załącznika Załącznik nr 14 WYKAZ USŁUG, O KTÓRYCH MOWA W ART. 17 UST. 1 PKT 8 USTAWY Poz. Symbol PKWiU Nazwa usługi (grupy usług) 1 bez względu na symbol PKWiU Usługi w zakresie przenoszenia uprawnień do emisji gazów cieplarnianych, o których mowa w ustawie z dnia 12 czerwca 2015 r. o systemie handlu uprawnieniami do emisji gazów cieplarnianych (Dz. U. poz. 1223 oraz z 2016 r. poz. 266, 542, 1579 i 1948) 2 41.00.30.0 Roboty budowlane związane ze wznoszeniem budynków mieszkalnych (prace związane z budową nowych budynków, przebudową lub remontem istniejących budynków) 3 41.00.40.0 Roboty budowlane związane ze wznoszeniem budynków niemieszkalnych (prace związane z budową nowych budynków, przebudową lub remontem istniejących budynków) 4 42.11.20.0 Roboty ogólnobudowlane związane z budową autostrad, dróg, ulic i innych dróg dla pojazdów i pieszych oraz budową pasów startowych 5 42.12.20.0 Roboty ogólnobudowlane związane z budową dróg szynowych i kolei podziemnej 6 42.13.20.0 Roboty ogólnobudowlane związane z budową mostów i tuneli 7 42.21.21.0 Roboty ogólnobudowlane związane z budową rurociągów przesyłowych 8 42.21.22.0 Roboty ogólnobudowlane związane z budową sieci rozdzielczych, włączając prace pomocnicze 9 42.21.23.0 Roboty ogólnobudowlane związane z budową systemów irygacyjnych (kanałów), magistrali i linii wodociągowych, obiektów do uzdatniania wody i oczyszczania ścieków oraz stacji pomp 10 42.21.24.0 Roboty związane z wierceniem studni i ujęć wodnych oraz instalowaniem zbiorników septycznych 11 42.22.21.0 Roboty ogólnobudowlane związane z budową przesyłowych linii telekomunikacyjnych i elektroenergetycznych 12 42.22.22.0 Roboty ogólnobudowlane związane z budową rozdzielczych linii telekomunikacyjnych i elektroenergetycznych 13 42.22.23.0 Roboty ogólnobudowlane związane z budową elektrowni 14 42.91.20.0 Roboty ogólnobudowlane związane z budową nabrzeży, portów, tam, śluz i związanych z nimi obiektów hydrotechnicznych 15 42.99.21.0 Roboty ogólnobudowlane związane z budową obiektów produkcyjnych i górniczych 16 42.99.22.0 Roboty ogólnobudowlane związane z budową stadionów i boisk sportowych 17 42.99.29.0 Roboty ogólnobudowlane związane z budową pozostałych obiektów inżynierii lądowej i wodnej, gdzie indziej niesklasyfikowane 18 43.11.10.0 Roboty związane z rozbiórką i burzeniem obiektów budowlanych 19 43.12.11.0 Roboty związane z przygotowaniem terenu pod budowę, z wyłączeniem robót ziemnych 20 43.12.12.0 Roboty ziemne: roboty związane z kopaniem rowów i wykopów oraz przemieszczaniem ziemi 21 43.13.10.0 Roboty związane z wykonywaniem wykopów i wierceń geologiczno-inżynierskich 22 43.21.10.1 Roboty związane z wykonywaniem instalacji elektrycznych służących bezpieczeństwu 23 43.21.10.2 Roboty związane z wykonywaniem pozostałych instalacji elektrycznych 24 43.22.11.0 Roboty związane z wykonywaniem instalacji wodno-kanalizacyjnych i odwadniających 25 43.22.12.0 Roboty związane z wykonywaniem instalacji cieplnych, wentylacyjnych i klimatyzacyjnych 26 43.22.20.0 Roboty związane z wykonywaniem instalacji gazowych 27 43.29.11.0 Roboty związane z zakładaniem izolacji 28 43.29.12.0 Roboty związane z zakładaniem ogrodzeń 29 43.29.19.0 Pozostałe roboty instalacyjne, gdzie indziej niesklasyfikowane 30 43.31.10.0 Roboty tynkarskie 31 43.32.10.0 Roboty instalacyjne stolarki budowlanej 32 43.33.10.0 Roboty związane z wykładaniem posadzek i oblicowywaniem ścian 33 43.33.21.0 Roboty związane z wykładaniem podłóg i ścian lastryko, marmurem, granitem lub łupkiem 34 43.33.29.0 Pozostałe roboty związane z wykładaniem podłóg i ścian (włączając tapetowanie), gdzie indziej niesklasyfikowane 35 43.34.10.0 Roboty malarskie 36 43.34.20.0 Roboty szklarskie 37 43.39.11.0 Roboty związane z wykonywaniem elementów dekoracyjnych 38 43.39.19.0 Roboty związane z wykonywaniem pozostałych wykończeniowych robót budowlanych, gdzie indziej niesklasyfikowanych 39 43.91.11.0 Roboty związane z wykonywaniem konstrukcji dachowych 40 43.91.19.0 Roboty związane z wykonywaniem pozostałych prac dekarskich 41 43.99.10.0 Roboty związane z zakładaniem izolacji przeciwwilgociowych i wodochronnych 42 43.99.20.0 Roboty związane z montowaniem i demontowaniem rusztowań 43 43.99.30.0 Roboty związane z fundamentowaniem, włączając wbijanie pali 44 43.99.40.0 Roboty betoniarskie 45 43.99.50.0 Roboty związane ze wznoszeniem konstrukcji stalowych 46 43.99.60.0 Roboty związane ze wznoszeniem konstrukcji z cegieł i kamienia 47 43.99.70.0 Roboty związane z montażem i wznoszeniem konstrukcji z elementów prefabrykowanych 48 43.99.90.0 Roboty związane z wykonywaniem pozostałych specjalistycznych robót budowlanych, gdzie indziej niesklasyfikowanych Pokaż całość var tree = [ { \"id\" : \"part_1\", \"title\" : \"Treść ustawy\", \"type\": \"part\", \"symbol\" : \"part_1\", \"children\" : [ {\"id\": \"arti_1\",\"symbol\": \"arti_1\",\"type\": \"arti\",\"name\": \"1\",\"title\": \"Art. 1.\",\"children\": [{\"id\": \"arti_1-pint_1\",\"symbol\": \"pint_1\",\"type\": \"pint\",\"name\": \"1\",\"title\": \"1)\",\"children\": [{\"id\": \"arti_1-pint_1-lett_a\",\"symbol\": \"lett_a\",\"type\": \"lett\",\"name\": \"a\",\"title\": \"a)\"},{\"id\": \"arti_1-pint_1-lett_b\",\"symbol\": \"lett_b\",\"type\": \"lett\",\"name\": \"b\",\"title\": \"b)\"},{\"id\": \"arti_1-pint_1-lett_c\",\"symbol\": \"lett_c\",\"type\": \"lett\",\"name\": \"c\",\"title\": \"c)\"},{\"id\": \"arti_1-pint_1-lett_d\",\"symbol\": \"lett_d\",\"type\": \"lett\",\"name\": \"d\",\"title\": \"d)\"}]},{\"id\": \"arti_1-pint_2\",\"symbol\": \"pint_2\",\"type\": \"pint\",\"name\": \"2\",\"title\": \"2)\"},{\"id\": \"arti_1-pint_3\",\"symbol\": \"pint_3\",\"type\": \"pint\",\"name\": \"3\",\"title\": \"3)\",\"children\": [{\"id\": \"arti_1-pint_3-lett_a\",\"symbol\": \"lett_a\",\"type\": \"lett\",\"name\": \"a\",\"title\": \"a)\"},{\"id\": \"arti_1-pint_3-lett_b\",\"symbol\": \"lett_b\",\"type\": \"lett\",\"name\": \"b\",\"title\": \"b)\"}]},{\"id\": \"arti_1-pint_4\",\"symbol\": \"pint_4\",\"type\": \"pint\",\"name\": \"4\",\"title\": \"4)\",\"children\": [{\"id\": \"arti_1-pint_4-lett_a\",\"symbol\": \"lett_a\",\"type\": \"lett\",\"name\": \"a\",\"title\": \"a)\"},{\"id\": \"arti_1-pint_4-lett_b\",\"symbol\": \"lett_b\",\"type\": \"lett\",\"name\": \"b\",\"title\": \"b)\"}]},{\"id\": \"arti_1-pint_5\",\"symbol\": \"pint_5\",\"type\": \"pint\",\"name\": \"5\",\"title\": \"5)\",\"children\": [{\"id\": \"arti_1-pint_5-lett_a\",\"symbol\": \"lett_a\",\"type\": \"lett\",\"name\": \"a\",\"title\": \"a)\"},{\"id\": \"arti_1-pint_5-lett_b\",\"symbol\": \"lett_b\",\"type\": \"lett\",\"name\": \"b\",\"title\": \"b)\"},{\"id\": \"arti_1-pint_5-lett_c\",\"symbol\": \"lett_c\",\"type\": \"lett\",\"name\": \"c\",\"title\": \"c)\"},{\"id\": \"arti_1-pint_5-lett_d\",\"symbol\": \"lett_d\",\"type\": \"lett\",\"name\": \"d\",\"title\": \"d)\"},{\"id\": \"arti_1-pint_5-lett_e\",\"symbol\": \"lett_e\",\"type\": \"lett\",\"name\": \"e\",\"title\": \"e)\"},{\"id\": \"arti_1-pint_5-lett_f\",\"symbol\": \"lett_f\",\"type\": \"lett\",\"name\": \"f\",\"title\": \"f)\"}]},{\"id\": \"arti_1-pint_6\",\"symbol\": \"pint_6\",\"type\": \"pint\",\"name\": \"6\",\"title\": \"6)\"},{\"id\": \"arti_1-pint_7\",\"symbol\": \"pint_7\",\"type\": \"pint\",\"name\": \"7\",\"title\": \"7)\"},{\"id\": \"arti_1-pint_8\",\"symbol\": \"pint_8\",\"type\": \"pint\",\"name\": \"8\",\"title\": \"8)\"},{\"id\": \"arti_1-pint_9\",\"symbol\": \"pint_9\",\"type\": \"pint\",\"name\": \"9\",\"title\": \"9)\"},{\"id\": \"arti_1-pint_10\",\"symbol\": \"pint_10\",\"type\": \"pint\",\"name\": \"10\",\"title\": \"10)\",\"children\": [{\"id\": \"arti_1-pint_10-lett_a\",\"symbol\": \"lett_a\",\"type\": \"lett\",\"name\": \"a\",\"title\": \"a)\"},{\"id\": \"arti_1-pint_10-lett_b\",\"symbol\": \"lett_b\",\"type\": \"lett\",\"name\": \"b\",\"title\": \"b)\"},{\"id\": \"arti_1-pint_10-lett_c\",\"symbol\": \"lett_c\",\"type\": \"lett\",\"name\": \"c\",\"title\": \"c)\"},{\"id\": \"arti_1-pint_10-lett_d\",\"symbol\": \"lett_d\",\"type\": \"lett\",\"name\": \"d\",\"title\": \"d)\"},{\"id\": \"arti_1-pint_10-lett_e\",\"symbol\": \"lett_e\",\"type\": \"lett\",\"name\": \"e\",\"title\": \"e)\"}]},{\"id\": \"arti_1-pint_11\",\"symbol\": \"pint_11\",\"type\": \"pint\",\"name\": \"11\",\"title\": \"11)\",\"children\": [{\"id\": \"arti_1-pint_11-lett_a\",\"symbol\": \"lett_a\",\"type\": \"lett\",\"name\": \"a\",\"title\": \"a)\"},{\"id\": \"arti_1-pint_11-lett_b\",\"symbol\": \"lett_b\",\"type\": \"lett\",\"name\": \"b\",\"title\": \"b)\"},{\"id\": \"arti_1-pint_11-lett_c\",\"symbol\": \"lett_c\",\"type\": \"lett\",\"name\": \"c\",\"title\": \"c)\"},{\"id\": \"arti_1-pint_11-lett_d\",\"symbol\": \"lett_d\",\"type\": \"lett\",\"name\": \"d\",\"title\": \"d)\"}]},{\"id\": \"arti_1-pint_12\",\"symbol\": \"pint_12\",\"type\": \"pint\",\"name\": \"12\",\"title\": \"12)\",\"children\": [{\"id\": \"arti_1-pint_12-lett_a\",\"symbol\": \"lett_a\",\"type\": \"lett\",\"name\": \"a\",\"title\": \"a)\"},{\"id\": \"arti_1-pint_12-lett_b\",\"symbol\": \"lett_b\",\"type\": \"lett\",\"name\": \"b\",\"title\": \"b)\"},{\"id\": \"arti_1-pint_12-lett_c\",\"symbol\": \"lett_c\",\"type\": \"lett\",\"name\": \"c\",\"title\": \"c)\"}]},{\"id\": \"arti_1-pint_13\",\"symbol\": \"pint_13\",\"type\": \"pint\",\"name\": \"13\",\"title\": \"13)\",\"children\": [{\"id\": \"arti_1-pint_13-lett_a\",\"symbol\": \"lett_a\",\"type\": \"lett\",\"name\": \"a\",\"title\": \"a)\"},{\"id\": \"arti_1-pint_13-lett_b\",\"symbol\": \"lett_b\",\"type\": \"lett\",\"name\": \"b\",\"title\": \"b)\"},{\"id\": \"arti_1-pint_13-lett_c\",\"symbol\": \"lett_c\",\"type\": \"lett\",\"name\": \"c\",\"title\": \"c)\"}]},{\"id\": \"arti_1-pint_14\",\"symbol\": \"pint_14\",\"type\": \"pint\",\"name\": \"14\",\"title\": \"14)\"},{\"id\": \"arti_1-pint_15\",\"symbol\": \"pint_15\",\"type\": \"pint\",\"name\": \"15\",\"title\": \"15)\",\"children\": [{\"id\": \"arti_1-pint_15-lett_a\",\"symbol\": \"lett_a\",\"type\": \"lett\",\"name\": \"a\",\"title\": \"a)\"},{\"id\": \"arti_1-pint_15-lett_b\",\"symbol\": \"lett_b\",\"type\": \"lett\",\"name\": \"b\",\"title\": \"b)\"}]},{\"id\": \"arti_1-pint_16\",\"symbol\": \"pint_16\",\"type\": \"pint\",\"name\": \"16\",\"title\": \"16)\",\"children\": [{\"id\": \"arti_1-pint_16-lett_a\",\"symbol\": \"lett_a\",\"type\": \"lett\",\"name\": \"a\",\"title\": \"a)\"},{\"id\": \"arti_1-pint_16-lett_b\",\"symbol\": \"lett_b\",\"type\": \"lett\",\"name\": \"b\",\"title\": \"b)\"},{\"id\": \"arti_1-pint_16-lett_c\",\"symbol\": \"lett_c\",\"type\": \"lett\",\"name\": \"c\",\"title\": \"c)\"}]},{\"id\": \"arti_1-pint_17\",\"symbol\": \"pint_17\",\"type\": \"pint\",\"name\": \"17\",\"title\": \"17)\",\"children\": [{\"id\": \"arti_1-pint_17-lett_a\",\"symbol\": \"lett_a\",\"type\": \"lett\",\"name\": \"a\",\"title\": \"a)\"},{\"id\": \"arti_1-pint_17-lett_b\",\"symbol\": \"lett_b\",\"type\": \"lett\",\"name\": \"b\",\"title\": \"b)\"}]},{\"id\": \"arti_1-pint_18\",\"symbol\": \"pint_18\",\"type\": \"pint\",\"name\": \"18\",\"title\": \"18)\",\"children\": [{\"id\": \"arti_1-pint_18-lett_a\",\"symbol\": \"lett_a\",\"type\": \"lett\",\"name\": \"a\",\"title\": \"a)\"},{\"id\": \"arti_1-pint_18-lett_b\",\"symbol\": \"lett_b\",\"type\": \"lett\",\"name\": \"b\",\"title\": \"b)\"},{\"id\": \"arti_1-pint_18-lett_c\",\"symbol\": \"lett_c\",\"type\": \"lett\",\"name\": \"c\",\"title\": \"c)\"},{\"id\": \"arti_1-pint_18-lett_d\",\"symbol\": \"lett_d\",\"type\": \"lett\",\"name\": \"d\",\"title\": \"d)\"},{\"id\": \"arti_1-pint_18-lett_e\",\"symbol\": \"lett_e\",\"type\": \"lett\",\"name\": \"e\",\"title\": \"e)\"},{\"id\": \"arti_1-pint_18-lett_f\",\"sy"
    }
  ],
  "definitions": [
    {
      "term": "w art. 86: a) w ust. 10b:",
      "definition": "w pkt 2 lit. b otrzymuje brzmienie: „ b) uwzględni kwotę podatku należnego z tytułu wewnątrzwspólnotowego nabycia towarów w deklaracji podatkowej, w której jest on obowiązany rozliczyć ten podatek, nie później niż w terminie 3 miesięcy od upływu miesiąca, w którym w odniesieniu do nabytych towarów powstał obowiązek podatkowy; ” , - pkt 3 otrzymuje brzmienie: „ 3) ust. 2 pkt 4 lit. a, b i d - powstaje zgodnie z ust. 10, pod warunkiem że podatnik uwzględni kwotę podatku należnego z tytułu tych transakcji w deklaracji podatkowej, w której jest on obowiązany rozliczyć ten podatek, nie później niż w terminie 3 miesięcy od upływu miesiąca, w którym w odniesieniu do nabytych towarów lub usług powstał obowiązek podatkowy. ” , b) po ust. 10h dodaje się ust. 10i w brzmieniu: „ 10i. W przypadku uwzględnienia przez podatnika kwoty podatku należnego w deklaracji podatkowej, w której jest on obowiązany rozliczyć ten podatek, w terminie późniejszym niż określony w ust. 10b pkt 2 lit. b i pkt 3, podatnik może odpowiednio zwiększyć kwotę podatku naliczonego w rozliczeniu za okres rozliczeniowy, w odniesieniu do którego nie upłynął jeszcze termin do złożenia deklaracji podatkowej. ”",
      "source_provision": "art1"
    }
  ]
}